[
  {
    "Lugares":"ABEJORRAL - ANTIOQUIA"
  },
  {
    "Lugares":"ABREGO - NORTE SANTANDER"
  },
  {
    "Lugares":"ABRIAQUI - ANTIOQUIA"
  },
  {
    "Lugares":"ACACIAS - META"
  },
  {
    "Lugares":"ACEVEDO - HUILA"
  },
  {
    "Lugares":"ACHI - BOLIVAR"
  },
  {
    "Lugares":"AGRADO - HUILA"
  },
  {
    "Lugares":"AGUA CLARA - NORTE SANTANDER"
  },
  {
    "Lugares":"AGUA DE DIOS - CUNDINAMARCA"
  },
  {
    "Lugares":"AGUACHICA - CESAR"
  },
  {
    "Lugares":"AGUACLARA - CASANARE"
  },
  {
    "Lugares":"AGUADA - SANTANDER"
  },
  {
    "Lugares":"AGUADA DE PABLO - ATLANTICO"
  },
  {
    "Lugares":"AGUADAS - CALDAS"
  },
  {
    "Lugares":"AGUAZUL - CASANARE"
  },
  {
    "Lugares":"AIPE - HUILA"
  },
  {
    "Lugares":"ALBAN - CUNDINAMARCA"
  },
  {
    "Lugares":"ALBANIA - GUAJIRA"
  },
  {
    "Lugares":"ALBANIA - CAQUETA"
  },
  {
    "Lugares":"ALBANIA CAMP LA ROSITA - GUAJIRA"
  },
  {
    "Lugares":"ALBANIA HOTEL WAYA - GUAJIRA"
  },
  {
    "Lugares":"ALCALA - VALLE DEL CAUCA"
  },
  {
    "Lugares":"ALDANA - NARIÑO"
  },
  {
    "Lugares":"ALEJANDRIA - ANTIOQUIA"
  },
  {
    "Lugares":"ALGARROBO - MAGDALENA"
  },
  {
    "Lugares":"ALGECIRAS - HUILA"
  },
  {
    "Lugares":"ALMAGUER - CAUCA"
  },
  {
    "Lugares":"ALMEIDA - BOYACA"
  },
  {
    "Lugares":"ALPUJARRA - TOLIMA"
  },
  {
    "Lugares":"ALTAGRACIA - RISARALDA"
  },
  {
    "Lugares":"ALTAMIRA - HUILA"
  },
  {
    "Lugares":"ALTOS DE DAZA - NARIÑO"
  },
  {
    "Lugares":"ALTAMIRA - ANTIOQUIA"
  },
  {
    "Lugares":"ALVARADO - TOLIMA"
  },
  {
    "Lugares":"AMAGA - ANTIOQUIA"
  },
  {
    "Lugares":"AMAIME - VALLE DEL CAUCA"
  },
  {
    "Lugares":"AMALFI - ANTIOQUIA"
  },
  {
    "Lugares":"AMBALEMA - TOLIMA"
  },
  {
    "Lugares":"ANAPOIMA - CUNDINAMARCA"
  },
  {
    "Lugares":"ANCUYA - NARIÑO"
  },
  {
    "Lugares":"ANDAGOYA - CHOCO"
  },
  {
    "Lugares":"ANDALUCIA - VALLE DEL CAUCA"
  },
  {
    "Lugares":"ANDES - ANTIOQUIA"
  },
  {
    "Lugares":"ANGANOY - NARIÑO"
  },
  {
    "Lugares":"ANGELOPOLIS - ANTIOQUIA"
  },
  {
    "Lugares":"ANGOSTURA - ANTIOQUIA"
  },
  {
    "Lugares":"ANOLAIMA - CUNDINAMARCA"
  },
  {
    "Lugares":"ANORI - ANTIOQUIA"
  },
  {
    "Lugares":"ANSERMA - CALDAS"
  },
  {
    "Lugares":"ANSERMA NUEVO - VALLE DEL CAUCA"
  },
  {
    "Lugares":"ANZA - ANTIOQUIA"
  },
  {
    "Lugares":"ANZOATEGUI - TOLIMA"
  },
  {
    "Lugares":"APARTADO - ANTIOQUIA"
  },
  {
    "Lugares":"APIA - RISARALDA"
  },
  {
    "Lugares":"APIAY - META"
  },
  {
    "Lugares":"APULO - CUNDINAMARCA"
  },
  {
    "Lugares":"AQUITANIA - BOYACA"
  },
  {
    "Lugares":"ARABIA - RISARALDA"
  },
  {
    "Lugares":"ARACATACA - MAGDALENA"
  },
  {
    "Lugares":"ARAGUANEY - CASANARE"
  },
  {
    "Lugares":"ARANZAZU - CALDAS"
  },
  {
    "Lugares":"ARARCA - BOLIVAR"
  },
  {
    "Lugares":"ARATOCA - SANTANDER"
  },
  {
    "Lugares":"ARAUCA - CALDAS"
  },
  {
    "Lugares":"ARAUCA - ARAUCA"
  },
  {
    "Lugares":"ARAUQUITA - ARAUCA"
  },
  {
    "Lugares":"ARBELAEZ - CUNDINAMARCA"
  },
  {
    "Lugares":"ARBOLEDA - NARIÑO"
  },
  {
    "Lugares":"ARBOLEDAS - NORTE SANTANDER"
  },
  {
    "Lugares":"ARBOLETES - ANTIOQUIA"
  },
  {
    "Lugares":"ARCABUCO - BOYACA"
  },
  {
    "Lugares":"ARGELIA - ANTIOQUIA"
  },
  {
    "Lugares":"ARGELIA - CAUCA"
  },
  {
    "Lugares":"ARGELIA - VALLE DEL CAUCA"
  },
  {
    "Lugares":"ARGÜELLO ALTO - NARIÑO"
  },
  {
    "Lugares":"ARIZONA - NARIÑO"
  },
  {
    "Lugares":"ARJONA - BOLIVAR"
  },
  {
    "Lugares":"ARJONA - CESAR"
  },
  {
    "Lugares":"ARMA - CALDAS"
  },
  {
    "Lugares":"ARMENIA - QUINDIO"
  },
  {
    "Lugares":"ARMENIA MANTEQUILLA - ANTIOQUIA"
  },
  {
    "Lugares":"ARMERO - GUAYABAL - TOLIMA"
  },
  {
    "Lugares":"ARROYO DE PIEDRA - ATLANTICO"
  },
  {
    "Lugares":"ARROYO DE PIEDRA - BOLIVAR"
  },
  {
    "Lugares":"ARROYO HONDO - BOLIVAR"
  },
  {
    "Lugares":"ASTILLEROS - NORTE SANTANDER"
  },
  {
    "Lugares":"ASTREA - CESAR"
  },
  {
    "Lugares":"ATACO - TOLIMA"
  },
  {
    "Lugares":"AYACUCHO - CESAR"
  },
  {
    "Lugares":"AYAPEL - CORDOBA"
  },
  {
    "Lugares":"BAJO CASANARE - NARIÑO"
  },
  {
    "Lugares":"BALBOA - CAUCA"
  },
  {
    "Lugares":"BALBOA - RISARALDA"
  },
  {
    "Lugares":"BARANOA - ATLANTICO"
  },
  {
    "Lugares":"BARAYA - HUILA"
  },
  {
    "Lugares":"BARBACOAS - NARIÑO"
  },
  {
    "Lugares":"BARBOSA - ANTIOQUIA"
  },
  {
    "Lugares":"BARBOSA - SANTANDER"
  },
  {
    "Lugares":"BARCELONA - QUINDIO"
  },
  {
    "Lugares":"BARICHARA - SANTANDER"
  },
  {
    "Lugares":"BARU POBLACION - BOLIVAR"
  },
  {
    "Lugares":"BARRAGAN - QUINDIO"
  },
  {
    "Lugares":"BARRANCA DE UPIA - META"
  },
  {
    "Lugares":"BARRANCABERMEJA - SANTANDER"
  },
  {
    "Lugares":"BARRANCAS - GUAJIRA"
  },
  {
    "Lugares":"BARRANCO - BOLIVAR"
  },
  {
    "Lugares":"BARRANQUILLA - ATLANTICO"
  },
  {
    "Lugares":"BAYUNCA - BOLIVAR"
  },
  {
    "Lugares":"BECERRIL - CESAR"
  },
  {
    "Lugares":"BELALCAZAR - CALDAS"
  },
  {
    "Lugares":"BELALCAZAR - CAUCA"
  },
  {
    "Lugares":"BELEN - BOYACA"
  },
  {
    "Lugares":"BELEN - HUILA"
  },
  {
    "Lugares":"BELEN - NARIÑO"
  },
  {
    "Lugares":"BELEN DE ANDAQUIES - CAQUETA"
  },
  {
    "Lugares":"BELEN DE UMBRIA - RISARALDA"
  },
  {
    "Lugares":"BELENCITO - BOYACA"
  },
  {
    "Lugares":"BELLO - ANTIOQUIA"
  },
  {
    "Lugares":"BELMIRA - ANTIOQUIA"
  },
  {
    "Lugares":"BELTRAN - CUNDINAMARCA"
  },
  {
    "Lugares":"BERASTEGUI - CORDOBA"
  },
  {
    "Lugares":"BERBEO - BOYACA"
  },
  {
    "Lugares":"BERMEJAL - NARIÑO"
  },
  {
    "Lugares":"BERRUECOS - NARIÑO"
  },
  {
    "Lugares":"BETANIA - ANTIOQUIA"
  },
  {
    "Lugares":"BETANIA - HUILA"
  },
  {
    "Lugares":"BETEITIVA - BOYACA"
  },
  {
    "Lugares":"BETULIA - ANTIOQUIA"
  },
  {
    "Lugares":"BETULIA - SANTANDER"
  },
  {
    "Lugares":"BETULIA - SUCRE"
  },
  {
    "Lugares":"BITUIMA - CUNDINAMARCA"
  },
  {
    "Lugares":"BOAVITA - BOYACA"
  },
  {
    "Lugares":"BOCHALEMA - NORTE SANTANDER"
  },
  {
    "Lugares":"BOGOTA D.C. - CUNDINAMARCA"
  },
  {
    "Lugares":"BOJACA - CUNDINAMARCA"
  },
  {
    "Lugares":"BOLIVAR - CAUCA"
  },
  {
    "Lugares":"BOLIVAR - SANTANDER"
  },
  {
    "Lugares":"BOLIVAR - VALLE DEL CAUCA"
  },
  {
    "Lugares":"BOLIVIA - CALDAS"
  },
  {
    "Lugares":"BOLO ALISAL - PALMIRA - VALLE DEL CAUCA"
  },
  {
    "Lugares":"BOLO ITALIA \/ PALMIRA - VALLE DEL CAUCA"
  },
  {
    "Lugares":"BOLO SAN ISIDRO - PALMIRA - VALLE DEL CAUCA"
  },
  {
    "Lugares":"BOLOMBOLO - ANTIOQUIA"
  },
  {
    "Lugares":"BONZA - BOYACA"
  },
  {
    "Lugares":"BOSCONIA - CESAR"
  },
  {
    "Lugares":"BOTANILLA - NARIÑO"
  },
  {
    "Lugares":"BOYACA - BOYACA"
  },
  {
    "Lugares":"BRICEÑO - ANTIOQUIA"
  },
  {
    "Lugares":"BRICEÑO - CUNDINAMARCA"
  },
  {
    "Lugares":"BRICEÑO - BOYACA"
  },
  {
    "Lugares":"BRUSELAS - HUILA"
  },
  {
    "Lugares":"BRUSELAS - NARIÑO"
  },
  {
    "Lugares":"BUCARAMANGA - SANTANDER"
  },
  {
    "Lugares":"BUCARASICA - NORTE SANTANDER"
  },
  {
    "Lugares":"BUENAVENTURA - VALLE DEL CAUCA"
  },
  {
    "Lugares":"BUENAVISTA - GUAJIRA"
  },
  {
    "Lugares":"BUENAVISTA - SUCRE"
  },
  {
    "Lugares":"BUENAVISTA - BOYACA"
  },
  {
    "Lugares":"BUENAVISTA - CORDOBA"
  },
  {
    "Lugares":"BUENAVISTA - QUINDIO"
  },
  {
    "Lugares":"BUENOS AIRES - CAUCA"
  },
  {
    "Lugares":"BUENOS AIRES - TOLIMA"
  },
  {
    "Lugares":"BUESACO - NARIÑO"
  },
  {
    "Lugares":"BUESAQUILLO - NARIÑO"
  },
  {
    "Lugares":"BUGA - VALLE DEL CAUCA"
  },
  {
    "Lugares":"BUGALAGRANDE - VALLE DEL CAUCA"
  },
  {
    "Lugares":"BURITACA - MAGDALENA"
  },
  {
    "Lugares":"BURITICA - ANTIOQUIA"
  },
  {
    "Lugares":"BUSBANZA - BOYACA"
  },
  {
    "Lugares":"CABRERA - NARIÑO"
  },
  {
    "Lugares":"CABRERA - CUNDINAMARCA"
  },
  {
    "Lugares":"CABRERA - SANTANDER"
  },
  {
    "Lugares":"CACERES - ANTIOQUIA"
  },
  {
    "Lugares":"CACHIPAY - CUNDINAMARCA"
  },
  {
    "Lugares":"CACHIRA - NORTE SANTANDER"
  },
  {
    "Lugares":"CACOTA - NORTE SANTANDER"
  },
  {
    "Lugares":"CAICEDO - ANTIOQUIA"
  },
  {
    "Lugares":"CAICEDONIA - VALLE DEL CAUCA"
  },
  {
    "Lugares":"CAIMITOS - SUCRE"
  },
  {
    "Lugares":"CAJAMARCA - TOLIMA"
  },
  {
    "Lugares":"CAJIBIO - CAUCA"
  },
  {
    "Lugares":"CAJICA - CUNDINAMARCA"
  },
  {
    "Lugares":"CALABAZO - MAGDALENA"
  },
  {
    "Lugares":"CALAMAR - BOLIVAR"
  },
  {
    "Lugares":"CALARCA - QUINDIO"
  },
  {
    "Lugares":"CALDAS - ANTIOQUIA"
  },
  {
    "Lugares":"CALDAS - BOYACA"
  },
  {
    "Lugares":"CALDONO - CAUCA"
  },
  {
    "Lugares":"CALI - VALLE DEL CAUCA"
  },
  {
    "Lugares":"CALIBIO - CAUCA"
  },
  {
    "Lugares":"CALOTO - CAUCA"
  },
  {
    "Lugares":"CAMPAMENTO - ANTIOQUIA"
  },
  {
    "Lugares":"CAMPANA - GUAJIRA"
  },
  {
    "Lugares":"CAMPECHE - ATLANTICO"
  },
  {
    "Lugares":"CAMPO 23 - SANTANDER"
  },
  {
    "Lugares":"CAMPO DE LA CRUZ - ATLANTICO"
  },
  {
    "Lugares":"CAMPOALEGRE - HUILA"
  },
  {
    "Lugares":"CAMPOHERMOSO - BOYACA"
  },
  {
    "Lugares":"CANALETE - CORDOBA"
  },
  {
    "Lugares":"CANCHALA - NARIÑO"
  },
  {
    "Lugares":"CANDELARIA - ATLANTICO"
  },
  {
    "Lugares":"CANDELARIA - VALLE DEL CAUCA"
  },
  {
    "Lugares":"CANTAGALLO - BOLIVAR"
  },
  {
    "Lugares":"CAÑASGORDAS - ANTIOQUIA"
  },
  {
    "Lugares":"CAÑO LIMON - ARAUCA"
  },
  {
    "Lugares":"CAPARRAPI - CUNDINAMARCA"
  },
  {
    "Lugares":"CAPELLANIA - CUNDINAMARCA"
  },
  {
    "Lugares":"CAPITANEJO - SANTANDER"
  },
  {
    "Lugares":"CAQUEZA - CUNDINAMARCA"
  },
  {
    "Lugares":"CARACOLI - ATLANTICO"
  },
  {
    "Lugares":"CARACOLI - ANTIOQUIA"
  },
  {
    "Lugares":"CARACOLICITO - CESAR"
  },
  {
    "Lugares":"CARAMANTA - ANTIOQUIA"
  },
  {
    "Lugares":"CARCASI - SANTANDER"
  },
  {
    "Lugares":"CAREPA - ANTIOQUIA"
  },
  {
    "Lugares":"CARLOSAMA - NARIÑO"
  },
  {
    "Lugares":"CARMEN DE APICALA - TOLIMA"
  },
  {
    "Lugares":"CARMEN DE CARUPA - CUND."
  },
  {
    "Lugares":"CARMEN DE VIBORAL - ANTIOQUIA"
  },
  {
    "Lugares":"CAROLINA DEL PRINCIPE - ANT."
  },
  {
    "Lugares":"CARRETO - BOLIVAR"
  },
  {
    "Lugares":"CARRILLO - CORDOBA"
  },
  {
    "Lugares":"CARTAGENA - BOLIVAR"
  },
  {
    "Lugares":"CARTAGENA DEL CHAIRA - CAQUETA"
  },
  {
    "Lugares":"CARTAGO - VALLE DEL CAUCA"
  },
  {
    "Lugares":"CASABIANCA - TOLIMA"
  },
  {
    "Lugares":"CASACARA - CESAR"
  },
  {
    "Lugares":"CASCAJAL - ATLANTICO"
  },
  {
    "Lugares":"CASTILLA - TOLIMA"
  },
  {
    "Lugares":"CASTILLA LA NUEVA - META"
  },
  {
    "Lugares":"CATAMBUCO - NARIÑO"
  },
  {
    "Lugares":"CAUCASECO - PALMIRA - VALLE DEL CAUCA"
  },
  {
    "Lugares":"CAUCASIA - ANTIOQUIA"
  },
  {
    "Lugares":"CAVASA - VALLE DEL CAUCA"
  },
  {
    "Lugares":"CEMEX TRANSPORTES\/ GUALANDAY - TOL."
  },
  {
    "Lugares":"CERETE - CORDOBA"
  },
  {
    "Lugares":"CERINZA - BOYACA"
  },
  {
    "Lugares":"CEROTAL - NARIÑO"
  },
  {
    "Lugares":"CERRITO - SANTANDER"
  },
  {
    "Lugares":"CERRITOS - RISARALDA"
  },
  {
    "Lugares":"CERRO DE SAN ANTONIO - MAG."
  },
  {
    "Lugares":"CERROMATOSO - CORDOBA"
  },
  {
    "Lugares":"CERTEGUI - CHOCO"
  },
  {
    "Lugares":"CHACHAGÜI - NARIÑO"
  },
  {
    "Lugares":"CHALAN - SUCRE"
  },
  {
    "Lugares":"CHAPACUAL - NARIÑO"
  },
  {
    "Lugares":"CHAPARRAL - TOLIMA"
  },
  {
    "Lugares":"CHARALA - SANTANDER"
  },
  {
    "Lugares":"CHIA - CUNDINAMARCA"
  },
  {
    "Lugares":"CHIBOLO - MAGDALENA"
  },
  {
    "Lugares":"CHICORAL - TOLIMA"
  },
  {
    "Lugares":"CHICHIMENE - META"
  },
  {
    "Lugares":"CHIGORODO - ANTIOQUIA"
  },
  {
    "Lugares":"CHIMA - CORDOBA"
  },
  {
    "Lugares":"CHIMA - SANTANDER"
  },
  {
    "Lugares":"CHIMICHAGUA - CESAR"
  },
  {
    "Lugares":"CHINACOTA - NORTE SANTANDER"
  },
  {
    "Lugares":"CHINAUTA - CUNDINAMARCA"
  },
  {
    "Lugares":"CHINAVITA - BOYACA"
  },
  {
    "Lugares":"CHINCHINA - CALDAS"
  },
  {
    "Lugares":"CHINU - CORDOBA"
  },
  {
    "Lugares":"CHIPAQUE - CUNDINAMARCA"
  },
  {
    "Lugares":"CHIPATA - SANTANDER"
  },
  {
    "Lugares":"CHIQUINQUIRA - BOYACA"
  },
  {
    "Lugares":"CHIQUIZA - BOYACA"
  },
  {
    "Lugares":"CHIRIGUANA - CESAR"
  },
  {
    "Lugares":"CHISCAS - BOYACA"
  },
  {
    "Lugares":"CHITA - BOYACA"
  },
  {
    "Lugares":"CHITAGA - NORTE SANTANDER"
  },
  {
    "Lugares":"CHITARAQUE - BOYACA"
  },
  {
    "Lugares":"CHIVATA - BOYACA"
  },
  {
    "Lugares":"CHIVOR - BOYACA"
  },
  {
    "Lugares":"CHOACHI - CUNDINAMARCA"
  },
  {
    "Lugares":"CHOCONTA - CUNDINAMARCA"
  },
  {
    "Lugares":"CHORRILLO - NARIÑO"
  },
  {
    "Lugares":"CHUSACA - CUNDINAMARCA"
  },
  {
    "Lugares":"CIENAGA - MAGDALENA"
  },
  {
    "Lugares":"CIENAGA DE ORO - CORDOBA"
  },
  {
    "Lugares":"CIENEGA - BOYACA"
  },
  {
    "Lugares":"CIMARRONES - NARIÑO"
  },
  {
    "Lugares":"CIMITARRA - SANTANDER"
  },
  {
    "Lugares":"CIRCASIA - QUINDIO"
  },
  {
    "Lugares":"CISNEROS - VALLE DEL CAUCA"
  },
  {
    "Lugares":"CISNEROS - ANTIOQUIA"
  },
  {
    "Lugares":"CIUDAD BOLIVAR - ANTIOQUIA"
  },
  {
    "Lugares":"CIUDAD DEL CAMPO - PALMIRA - VALLE DEL CAUCA"
  },
  {
    "Lugares":"CLEMENCIA - BOLIVAR"
  },
  {
    "Lugares":"COCONUCO - CAUCA"
  },
  {
    "Lugares":"COCORNA - ANTIOQUIA"
  },
  {
    "Lugares":"CODAZZI - CESAR"
  },
  {
    "Lugares":"COELLO - TOLIMA"
  },
  {
    "Lugares":"COGUA - CUNDINAMARCA"
  },
  {
    "Lugares":"COLOMBIA - HUILA"
  },
  {
    "Lugares":"COLON - PUTUMAYO"
  },
  {
    "Lugares":"COLON GENOVA - NARIÑO"
  },
  {
    "Lugares":"COLOSO - SUCRE"
  },
  {
    "Lugares":"COMBITA - BOYACA"
  },
  {
    "Lugares":"CONCEPCION - ANTIOQUIA"
  },
  {
    "Lugares":"CONCEPCION - SANTANDER"
  },
  {
    "Lugares":"CONCORDIA - ANTIOQUIA"
  },
  {
    "Lugares":"CONCORDIA - MAGDALENA"
  },
  {
    "Lugares":"CONDOTO - CHOCO"
  },
  {
    "Lugares":"CONFINES - SANTANDER"
  },
  {
    "Lugares":"CONSACA - NARIÑO"
  },
  {
    "Lugares":"CONTRATACION - SANTANDER"
  },
  {
    "Lugares":"CONVENCION - NORTE SANTANDER"
  },
  {
    "Lugares":"COPACABANA - ANTIOQUIA"
  },
  {
    "Lugares":"COPER - BOYACA"
  },
  {
    "Lugares":"COPEY - CESAR"
  },
  {
    "Lugares":"CORDOBA - NARIÑO"
  },
  {
    "Lugares":"CORDOBA - QUINDIO"
  },
  {
    "Lugares":"CORDOBITA - MAGDALENA"
  },
  {
    "Lugares":"CORINTO - CAUCA"
  },
  {
    "Lugares":"COROMORO - SANTANDER"
  },
  {
    "Lugares":"COROZAL - SUCRE"
  },
  {
    "Lugares":"CORRALES - BOYACA"
  },
  {
    "Lugares":"COSTA RICA - VALLE DEL CAUCA"
  },
  {
    "Lugares":"COTA - CUNDINAMARCA"
  },
  {
    "Lugares":"COTORRA - CORDOBA"
  },
  {
    "Lugares":"COVARACHIA - BOYACA"
  },
  {
    "Lugares":"COVEÑAS - SUCRE"
  },
  {
    "Lugares":"COYAIMA - TOLIMA"
  },
  {
    "Lugares":"CRUZ ARADA - NARIÑO"
  },
  {
    "Lugares":"CRUZ DE AMARILLO - NARIÑO"
  },
  {
    "Lugares":"CUASPUD - NARIÑO"
  },
  {
    "Lugares":"CUATRO VIENTOS - CESAR"
  },
  {
    "Lugares":"CUBARA - BOYACA"
  },
  {
    "Lugares":"CUBARRAL - META"
  },
  {
    "Lugares":"CUBIJAN BAJO - NARIÑO"
  },
  {
    "Lugares":"CUCAITA - BOYACA"
  },
  {
    "Lugares":"CUCUNUBA - CUNDINAMARCA"
  },
  {
    "Lugares":"CUCUTA - NORTE SANTANDER"
  },
  {
    "Lugares":"CUCUTILLA - NORTE SANTANDER"
  },
  {
    "Lugares":"CUESTECITA - GUAJIRA"
  },
  {
    "Lugares":"CUITIVA - BOYACA"
  },
  {
    "Lugares":"CUJACAL - NARIÑO"
  },
  {
    "Lugares":"CUJACAL BAJO - NARIÑO"
  },
  {
    "Lugares":"CUJACAL CENTRO - NARIÑO"
  },
  {
    "Lugares":"CUMARAL - META"
  },
  {
    "Lugares":"CUMBAL - NARIÑO"
  },
  {
    "Lugares":"CUMBITARA - NARIÑO"
  },
  {
    "Lugares":"CUNDAY - TOLIMA"
  },
  {
    "Lugares":"CUPIAGUA - CASANARE"
  },
  {
    "Lugares":"CURILLO - CAQUETA"
  },
  {
    "Lugares":"CURITI - SANTANDER"
  },
  {
    "Lugares":"CURRULAO - ANTIOQUIA"
  },
  {
    "Lugares":"CURUMANI - CESAR"
  },
  {
    "Lugares":"CUSIANA - CASANARE"
  },
  {
    "Lugares":"DABEIBA - ANTIOQUIA"
  },
  {
    "Lugares":"DAGUA - VALLE DEL CAUCA"
  },
  {
    "Lugares":"DAPA - VALLE DEL CAUCA"
  },
  {
    "Lugares":"DARIEN - VALLE DEL CAUCA"
  },
  {
    "Lugares":"DIBULLA - GUAJIRA"
  },
  {
    "Lugares":"DISTRACCION - GUAJIRA"
  },
  {
    "Lugares":"DOIMA - TOLIMA"
  },
  {
    "Lugares":"DOLORES - NARIÑO"
  },
  {
    "Lugares":"DOLORES - TOLIMA"
  },
  {
    "Lugares":"DON MATIAS - ANTIOQUIA"
  },
  {
    "Lugares":"DORADAL - ANTIOQUIA"
  },
  {
    "Lugares":"DOS QUEBRADAS - RISARALDA"
  },
  {
    "Lugares":"DRUMOND - MAGDALENA"
  },
  {
    "Lugares":"DUITAMA - BOYACA"
  },
  {
    "Lugares":"DURANIA - NORTE SANTANDER"
  },
  {
    "Lugares":"EBEJICO - ANTIOQUIA"
  },
  {
    "Lugares":"ECOPETROL CICUCO - BOLIVAR"
  },
  {
    "Lugares":"ECOPETROL KM. 17 - HUILA"
  },
  {
    "Lugares":"EL AGUILA - VALLE DEL CAUCA"
  },
  {
    "Lugares":"EL BAGRE - ANTIOQUIA"
  },
  {
    "Lugares":"EL BAJITO - NARIÑO"
  },
  {
    "Lugares":"EL BANCO - MAGDALENA"
  },
  {
    "Lugares":"EL BORDO - CAUCA"
  },
  {
    "Lugares":"EL CABUYAL - VALLE DEL CAUCA"
  },
  {
    "Lugares":"EL CAGUAN - HUILA"
  },
  {
    "Lugares":"EL CAIRO - VALLE DEL CAUCA"
  },
  {
    "Lugares":"EL CAMPANERO - NARIÑO"
  },
  {
    "Lugares":"EL CAPULI - NARIÑO"
  },
  {
    "Lugares":"EL CARMELO - VALLE DEL CAUCA"
  },
  {
    "Lugares":"EL CARMEN - NORTE SANTANDER"
  },
  {
    "Lugares":"EL CARMEN \/ KM. 30 - VALLE DEL CAUCA"
  },
  {
    "Lugares":"EL CARMEN DE ATRATO - CHOCO"
  },
  {
    "Lugares":"EL CARMEN DE BOLIVAR - BOLIVAR"
  },
  {
    "Lugares":"EL CARMEN DE CHUCURI - S\/DER."
  },
  {
    "Lugares":"EL CASTILLO - META"
  },
  {
    "Lugares":"EL CENTRO - SANTANDER"
  },
  {
    "Lugares":"EL CERRITO - VALLE DEL CAUCA"
  },
  {
    "Lugares":"EL CHARCO - NARIÑO"
  },
  {
    "Lugares":"EL CHARTE - CASANARE"
  },
  {
    "Lugares":"EL COCUY - BOYACA"
  },
  {
    "Lugares":"EL COLEGIO - CUNDINAMARCA"
  },
  {
    "Lugares":"EL CONTADERO - NARIÑO"
  },
  {
    "Lugares":"EL CRUCE - CESAR"
  },
  {
    "Lugares":"EL DIFICIL \/ ARIGUANI - MAGD."
  },
  {
    "Lugares":"EL DONCELLO - CAQUETA"
  },
  {
    "Lugares":"EL DORADO - META"
  },
  {
    "Lugares":"EL DOVIO - VALLE DEL CAUCA"
  },
  {
    "Lugares":"EL ENCANO - NARIÑO"
  },
  {
    "Lugares":"EL ESPINO - BOYACA"
  },
  {
    "Lugares":"EL ESPINO - NARIÑO"
  },
  {
    "Lugares":"EL ESTRECHO - CAUCA"
  },
  {
    "Lugares":"EL GUACAMAYO - SANTANDER"
  },
  {
    "Lugares":"EL GUAVIO - CUNDINAMARCA"
  },
  {
    "Lugares":"EL HORMIGUERO - CAUCA"
  },
  {
    "Lugares":"EL JUNCAL - HUILA"
  },
  {
    "Lugares":"EL LLANITO - SANTANDER"
  },
  {
    "Lugares":"EL MANZANO - BOYACA"
  },
  {
    "Lugares":"EL MOLINO - GUAJIRA"
  },
  {
    "Lugares":"EL MOLINO - CASANARE"
  },
  {
    "Lugares":"EL MUÑA - CUNDINAMARCA"
  },
  {
    "Lugares":"EL PASO - CESAR"
  },
  {
    "Lugares":"EL PAUJIL - CAQUETA"
  },
  {
    "Lugares":"EL PEÑOL - ANTIOQUIA"
  },
  {
    "Lugares":"EL PEÑOL - NARIÑO"
  },
  {
    "Lugares":"EL PEÑON - BOLIVAR"
  },
  {
    "Lugares":"EL PEÑON - CUNDINAMARCA"
  },
  {
    "Lugares":"EL PEÑON - SANTANDER"
  },
  {
    "Lugares":"EL PIÑON - MAGDALENA"
  },
  {
    "Lugares":"EL PLACER - VALLE DEL CAUCA"
  },
  {
    "Lugares":"EL PLAYON - SANTANDER"
  },
  {
    "Lugares":"EL QUEREMAL - VALLE DEL CAUCA"
  },
  {
    "Lugares":"EL REMOLINO - NARIÑO"
  },
  {
    "Lugares":"EL REPOSO ZONA URABA - ANT."
  },
  {
    "Lugares":"EL RETEN - MAGDALENA"
  },
  {
    "Lugares":"EL RETIRO - ANTIOQUIA"
  },
  {
    "Lugares":"EL ROBLE - SUCRE"
  },
  {
    "Lugares":"EL RODADERO - MAGDALENA"
  },
  {
    "Lugares":"EL ROSAL - CUNDINAMARCA"
  },
  {
    "Lugares":"EL ROSARIO - NARIÑO"
  },
  {
    "Lugares":"EL SALADITO - VALLE DEL CAUCA"
  },
  {
    "Lugares":"EL SISGA - CUNDINAMARCA"
  },
  {
    "Lugares":"EL TABLON - NARIÑO"
  },
  {
    "Lugares":"EL TAMBO - CAUCA"
  },
  {
    "Lugares":"EL TAMBO - NARIÑO"
  },
  {
    "Lugares":"EL TIGRE - PUTUMAYO"
  },
  {
    "Lugares":"EL TOTUMO ZONA URABA - ANT."
  },
  {
    "Lugares":"EL TRES ZONA URABA - ANT."
  },
  {
    "Lugares":"EL TRIUNFO - CAQUETA"
  },
  {
    "Lugares":"EL TRIUNFO - CUNDINAMARCA"
  },
  {
    "Lugares":"EL VIAJANO - CORDOBA"
  },
  {
    "Lugares":"EL VISO - BOLIVAR"
  },
  {
    "Lugares":"EL ZULIA - NORTE SANTANDER"
  },
  {
    "Lugares":"ENCINO - SANTANDER"
  },
  {
    "Lugares":"ENCISO - SANTANDER"
  },
  {
    "Lugares":"ENTRERRIOS - ANTIOQUIA"
  },
  {
    "Lugares":"ENVIGADO - ANTIOQUIA"
  },
  {
    "Lugares":"ESPINAL - TOLIMA"
  },
  {
    "Lugares":"ESPRIELLA - NARIÑO"
  },
  {
    "Lugares":"FACATATIVA - CUNDINAMARCA"
  },
  {
    "Lugares":"FALAN - TOLIMA"
  },
  {
    "Lugares":"FILADELFIA - CALDAS"
  },
  {
    "Lugares":"FILANDIA - QUINDIO"
  },
  {
    "Lugares":"FIRAVITOBA - BOYACA"
  },
  {
    "Lugares":"FLANDES - TOLIMA"
  },
  {
    "Lugares":"FLORENCIA - CAQUETA"
  },
  {
    "Lugares":"FLORENCIA - CALDAS"
  },
  {
    "Lugares":"FLORENCIA - CAUCA"
  },
  {
    "Lugares":"FLORESTA - BOYACA"
  },
  {
    "Lugares":"FLORIAN - SANTANDER"
  },
  {
    "Lugares":"FLORIDA - VALLE DEL CAUCA"
  },
  {
    "Lugares":"FLORIDA BLANCA - SANTANDER"
  },
  {
    "Lugares":"FOMEQUE - CUNDINAMARCA"
  },
  {
    "Lugares":"FONSECA - GUAJIRA"
  },
  {
    "Lugares":"FORTALECILLAS - HUILA"
  },
  {
    "Lugares":"FORTUL - ARAUCA"
  },
  {
    "Lugares":"FOSCA - CUNDINAMARCA"
  },
  {
    "Lugares":"FRANCISCO PIZARRO - NARIÑO"
  },
  {
    "Lugares":"FREDONIA - ANTIOQUIA"
  },
  {
    "Lugares":"FRESNO - TOLIMA"
  },
  {
    "Lugares":"FRONTINO - ANTIOQUIA"
  },
  {
    "Lugares":"FUENTE DE ORO - META"
  },
  {
    "Lugares":"FUNDACION - MAGDALENA"
  },
  {
    "Lugares":"FUNES - NARIÑO"
  },
  {
    "Lugares":"FUNZA - CUNDINAMARCA"
  },
  {
    "Lugares":"FUQUENE - CUNDINAMARCA"
  },
  {
    "Lugares":"FUSAGASUGA - CUNDINAMARCA"
  },
  {
    "Lugares":"GACHALA - CUNDINAMARCA"
  },
  {
    "Lugares":"GACHANCIPA - CUNDINAMARCA"
  },
  {
    "Lugares":"GACHANTIVA - BOYACA"
  },
  {
    "Lugares":"GACHETA - CUNDINAMARCA"
  },
  {
    "Lugares":"GAIRA - MAGDALENA"
  },
  {
    "Lugares":"GALAN - SANTANDER"
  },
  {
    "Lugares":"GALAPA - ATLANTICO"
  },
  {
    "Lugares":"GALERAS - SUCRE"
  },
  {
    "Lugares":"GALERAZAMBA - BOLIVAR"
  },
  {
    "Lugares":"GALLEGO - ATLANTICO"
  },
  {
    "Lugares":"GAMA - CUNDINAMARCA"
  },
  {
    "Lugares":"GAMARRA - CESAR"
  },
  {
    "Lugares":"GAMBITA - SANTANDER"
  },
  {
    "Lugares":"GAMBOTE - BOLIVAR"
  },
  {
    "Lugares":"GAMEZA - BOYACA"
  },
  {
    "Lugares":"GARAGOA - BOYACA"
  },
  {
    "Lugares":"GARZON - HUILA"
  },
  {
    "Lugares":"GENOVA - NARIÑO"
  },
  {
    "Lugares":"GENOVA - QUINDIO"
  },
  {
    "Lugares":"GENOY - NARIÑO"
  },
  {
    "Lugares":"GESELCA - GUAJIRA"
  },
  {
    "Lugares":"GIGANTE - HUILA"
  },
  {
    "Lugares":"GINEBRA - VALLE DEL CAUCA"
  },
  {
    "Lugares":"GIRALDO - ANTIOQUIA"
  },
  {
    "Lugares":"GIRARDOT - CUNDINAMARCA"
  },
  {
    "Lugares":"GIRARDOTA - ANTIOQUIA"
  },
  {
    "Lugares":"GIRON - SANTANDER"
  },
  {
    "Lugares":"GOMEZ PLATA - ANTIOQUIA"
  },
  {
    "Lugares":"GRAMALOTE - NORTE SANTANDER"
  },
  {
    "Lugares":"GRANADA - META"
  },
  {
    "Lugares":"GRANADA - ANTIOQUIA"
  },
  {
    "Lugares":"GRANADA - CUNDINAMARCA"
  },
  {
    "Lugares":null
  },
  {
    "Lugares":"GRANADILLO DE LUNAS - NARIÑO"
  },
  {
    "Lugares":"GUACA - SANTANDER"
  },
  {
    "Lugares":"GUACAMAYAL - MAGDALENA"
  },
  {
    "Lugares":"GUACAMAYAS - BOYACA"
  },
  {
    "Lugares":"GUACARI - VALLE DEL CAUCA"
  },
  {
    "Lugares":"GUACHACA - MAGDALENA"
  },
  {
    "Lugares":"GUACHAVES - NARIÑO"
  },
  {
    "Lugares":"GUACHENE - CAUCA"
  },
  {
    "Lugares":"GUACHETA - CUNDINAMARCA"
  },
  {
    "Lugares":"GUACHUCAL - NARIÑO"
  },
  {
    "Lugares":"GUADALUPE - ANTIOQUIA"
  },
  {
    "Lugares":"GUADALUPE - HUILA"
  },
  {
    "Lugares":"GUADALUPE - SANTANDER"
  },
  {
    "Lugares":"GUADUAS - CUNDINAMARCA"
  },
  {
    "Lugares":"GUAIRABAMBA - NARIÑO"
  },
  {
    "Lugares":"GUAITARILLA - NARIÑO"
  },
  {
    "Lugares":"GUALANDAY - TOLIMA"
  },
  {
    "Lugares":"GUALMATAN - NARIÑO"
  },
  {
    "Lugares":"GUALMATAN ALTO - NARIÑO"
  },
  {
    "Lugares":"GUAMAL - META"
  },
  {
    "Lugares":"GUAMAL - MAGDALENA"
  },
  {
    "Lugares":"GUAMO - TOLIMA"
  },
  {
    "Lugares":"GUANABANAL \/ PALMIRA - VALLE DEL CAUCA"
  },
  {
    "Lugares":"GUANAMA - NARIÑO"
  },
  {
    "Lugares":"GUAPOTA - SANTANDER"
  },
  {
    "Lugares":"GUARANDA - SUCRE"
  },
  {
    "Lugares":"GUARINOCITO - CALDAS"
  },
  {
    "Lugares":"GUARNE - ANTIOQUIA"
  },
  {
    "Lugares":"GUASCA - CUNDINAMARCA"
  },
  {
    "Lugares":"GUATAPE - ANTIOQUIA"
  },
  {
    "Lugares":"GUATAQUI - CUNDINAMARCA"
  },
  {
    "Lugares":"GUATAVITA - CUNDINAMARCA"
  },
  {
    "Lugares":"GUATEQUE - BOYACA"
  },
  {
    "Lugares":"GUATICA - RISARALDA"
  },
  {
    "Lugares":"GUAVATA - SANTANDER"
  },
  {
    "Lugares":"GUAYABAL - NARIÑO"
  },
  {
    "Lugares":"GUAYABAL DE SIQUIMA - CUND."
  },
  {
    "Lugares":"GUAYABETAL - CUNDINAMARCA"
  },
  {
    "Lugares":"GUAYACANAL - GUAJIRA"
  },
  {
    "Lugares":"GUAYATA - BOYACA"
  },
  {
    "Lugares":"GUEPSA - SANTANDER"
  },
  {
    "Lugares":"GÜICAN - BOYACA"
  },
  {
    "Lugares":"GUTIERREZ - CUNDINAMARCA"
  },
  {
    "Lugares":"HATILLO DE LOBA - BOLIVAR"
  },
  {
    "Lugares":"HATO - SANTANDER"
  },
  {
    "Lugares":"HATO COROZAL - CASANARE"
  },
  {
    "Lugares":"HATO NUEVO - GUAJIRA"
  },
  {
    "Lugares":"HELICONIA - ANTIOQUIA"
  },
  {
    "Lugares":"HERRAN - NORTE SANTANDER"
  },
  {
    "Lugares":"HERRERA - TOLIMA"
  },
  {
    "Lugares":"HERVEO - TOLIMA"
  },
  {
    "Lugares":"HIDROSOGAMOSO - SANTANDER"
  },
  {
    "Lugares":"HISPANIA - ANTIOQUIA"
  },
  {
    "Lugares":"HOBO - HUILA"
  },
  {
    "Lugares":"HONDA - TOLIMA"
  },
  {
    "Lugares":"HOTEL DECAMERON BARU - BOL."
  },
  {
    "Lugares":"IBAGUE - TOLIMA"
  },
  {
    "Lugares":"ICONONZO - TOLIMA"
  },
  {
    "Lugares":"ILES - NARIÑO"
  },
  {
    "Lugares":"IMUES - NARIÑO"
  },
  {
    "Lugares":"INGENIO CARMELITA - VALLE DEL CAUCA"
  },
  {
    "Lugares":"INGENIO DEL CAUCA INCAUCA - VALLE DEL CAUCA"
  },
  {
    "Lugares":"INGENIO LA CABAÑA - VALLE DEL CAUCA"
  },
  {
    "Lugares":"INGENIO MANUELITA - VALLE DEL CAUCA"
  },
  {
    "Lugares":"INGENIO MARIA LUISA - VALLE DEL CAUCA"
  },
  {
    "Lugares":"INGENIO MAYAGUEZ - VALLE DEL CAUCA"
  },
  {
    "Lugares":"INGENIO PICHICHI - VALLE DEL CAUCA"
  },
  {
    "Lugares":"INGENIO PROVIDENCIA - VALLE DEL CAUCA"
  },
  {
    "Lugares":"INGENIO RIOPAILA - VALLE DEL CAUCA"
  },
  {
    "Lugares":"INGENIO SAN CARLOS - VALLE DEL CAUCA"
  },
  {
    "Lugares":"INGENIO SEMICAÑA - VALLE DEL CAUCA"
  },
  {
    "Lugares":"INNATAS BAJO - NARIÑO"
  },
  {
    "Lugares":"INZA - CAUCA"
  },
  {
    "Lugares":"IPIALES - NARIÑO"
  },
  {
    "Lugares":"IQUIRA - HUILA"
  },
  {
    "Lugares":"IRRA - RISARALDA"
  },
  {
    "Lugares":"ISABEL LOPEZ - ATLANTICO"
  },
  {
    "Lugares":"ISCUANDE - NARIÑO"
  },
  {
    "Lugares":"ISNOS - HUILA"
  },
  {
    "Lugares":"ISTMINA - CHOCO"
  },
  {
    "Lugares":"ITAGUI - ANTIOQUIA"
  },
  {
    "Lugares":"ITUANGO - ANTIOQUIA"
  },
  {
    "Lugares":"IZA - BOYACA"
  },
  {
    "Lugares":"JAMBALO - CAUCA"
  },
  {
    "Lugares":"JAMUNDI - VALLE DEL CAUCA"
  },
  {
    "Lugares":"JARDIN - ANTIOQUIA"
  },
  {
    "Lugares":"JENESANO - BOYACA"
  },
  {
    "Lugares":"JERICO - ANTIOQUIA"
  },
  {
    "Lugares":"JERICO - BOYACA"
  },
  {
    "Lugares":"JESUS MARIA - SANTANDER"
  },
  {
    "Lugares":"JONGOVITO - NARIÑO"
  },
  {
    "Lugares":"JUAN DE ACOSTA - ATLANTICO"
  },
  {
    "Lugares":"JUAN MINA - ATLANTICO"
  },
  {
    "Lugares":"JUANCHITO \/ CALI - VALLE DEL CAUCA"
  },
  {
    "Lugares":"JUNIN - CUNDINAMARCA"
  },
  {
    "Lugares":"JUNIN - NARIÑO"
  },
  {
    "Lugares":"JURADO - NARIÑO"
  },
  {
    "Lugares":"KILOMETRO 12 VIA AL SUR - HUILA "
  },
  {
    "Lugares":"KILOMETRO 41 - CALDAS"
  },
  {
    "Lugares":"LA ALIANZA - NARIÑO"
  },
  {
    "Lugares":"LA APARTADA - CORDOBA"
  },
  {
    "Lugares":"LA ARGENTINA - HUILA"
  },
  {
    "Lugares":"LA AURORA - CESAR"
  },
  {
    "Lugares":"LA BELLA - QUINDIO"
  },
  {
    "Lugares":"LA BELLEZA - SANTANDER"
  },
  {
    "Lugares":"LA BOQUILLA - BOLIVAR"
  },
  {
    "Lugares":"LA BUITRERA \/ CALI - VALLE DEL CAUCA"
  },
  {
    "Lugares":"LA CALERA - CUNDINAMARCA"
  },
  {
    "Lugares":"LA CAPILLA - BOYACA"
  },
  {
    "Lugares":"LA CARO - CUNDINAMARCA"
  },
  {
    "Lugares":"LA CEJA - ANTIOQUIA"
  },
  {
    "Lugares":"LA CELIA - RISARALDA"
  },
  {
    "Lugares":"LA CHAMBA - TOLIMA"
  },
  {
    "Lugares":"LA CHAPARRERA - CASANARE"
  },
  {
    "Lugares":"LA CRUZ - NARIÑO"
  },
  {
    "Lugares":"LA CRUZADA - ANTIOQUIA"
  },
  {
    "Lugares":"LA CUMBRE - VALLE DEL CAUCA"
  },
  {
    "Lugares":"LA CUNCIA - META"
  },
  {
    "Lugares":"LA DOLORES \/ PALMIRA - VALLE DEL CAUCA"
  },
  {
    "Lugares":"LA DONJUANA - NORTE SANTANDER"
  },
  {
    "Lugares":"LA DORADA - CALDAS"
  },
  {
    "Lugares":"LA DORADA - PUTUMAYO"
  },
  {
    "Lugares":"LA ELVIRA \/ CALI - VALLE DEL CAUCA"
  },
  {
    "Lugares":"LA ESMERALDA - ARAUCA"
  },
  {
    "Lugares":"LA ESPERANZA - SANTANDER"
  },
  {
    "Lugares":"LA ESTANCIA - NARIÑO"
  },
  {
    "Lugares":"LA ESTRELLA - ANTIOQUIA"
  },
  {
    "Lugares":"LA FELISA - CALDAS"
  },
  {
    "Lugares":"LA FLORIDA - CUNDINAMARCA"
  },
  {
    "Lugares":"LA FLORIDA - NARIÑO"
  },
  {
    "Lugares":"LA FLORIDA - RISARALDA"
  },
  {
    "Lugares":"LA FORTUNA - SANTANDER"
  },
  {
    "Lugares":"LA GLORIA - CESAR"
  },
  {
    "Lugares":"LA GRAN VIA - MAGDALENA"
  },
  {
    "Lugares":"LA HERRADURA \/ PALMIRA - VALLE DEL CAUCA"
  },
  {
    "Lugares":"LA GUAYACANA - NARIÑO"
  },
  {
    "Lugares":"LA HORMIGA - PUTUMAYO"
  },
  {
    "Lugares":"LA JAGUA - HUILA"
  },
  {
    "Lugares":"LA JAGUA DE IBIRICO - CESAR"
  },
  {
    "Lugares":"LA JAGUA DEL PILAR - GUAJIRA"
  },
  {
    "Lugares":"LA LAGUNA - NARIÑO"
  },
  {
    "Lugares":"LA LLANADA - NARIÑO"
  },
  {
    "Lugares":"LA LOMA - CESAR"
  },
  {
    "Lugares":"LA MACARENA - META"
  },
  {
    "Lugares":"LA MATA - SANTANDER"
  },
  {
    "Lugares":"LA MERCED - CALDAS"
  },
  {
    "Lugares":"LA MESA - CUNDINAMARCA"
  },
  {
    "Lugares":"LA MESA DE LOS SANTOS - SANT."
  },
  {
    "Lugares":"LA MONTAÑITA - CAQUETA"
  },
  {
    "Lugares":"LA PAILA - VALLE DEL CAUCA"
  },
  {
    "Lugares":"LA PALMA - CUNDINAMARCA"
  },
  {
    "Lugares":"LA PALMA - NARIÑO"
  },
  {
    "Lugares":"LA PALMITA - TOLIMA"
  },
  {
    "Lugares":"LA PARADA - NORTE SANTANDER"
  },
  {
    "Lugares":"LA PAZ - CESAR"
  },
  {
    "Lugares":"LA PAZ - SANTANDER"
  },
  {
    "Lugares":"LA PEÑA - ATLANTICO"
  },
  {
    "Lugares":"LA PEÑA - CUNDINAMARCA"
  },
  {
    "Lugares":"LA PESQUERA - ARAUCA"
  },
  {
    "Lugares":"LA PINTADA - ANTIOQUIA"
  },
  {
    "Lugares":"LA PLATA - HUILA"
  },
  {
    "Lugares":"LA PLAYA - NORTE SANTANDER"
  },
  {
    "Lugares":"LA PUNTA - CUNDINAMARCA"
  },
  {
    "Lugares":"LA PUNTA - GUAJIRA"
  },
  {
    "Lugares":"LA SALINA - CASANARE"
  },
  {
    "Lugares":"LA SIERRA - TOLIMA"
  },
  {
    "Lugares":"LA SIERRA - ANTIOQUIA"
  },
  {
    "Lugares":"LA SIERRA - CAUCA"
  },
  {
    "Lugares":"LA SIERRITA - CESAR"
  },
  {
    "Lugares":"LA SILVIA - QUINDIO"
  },
  {
    "Lugares":"LA TABLAZA - ANTIOQUIA"
  },
  {
    "Lugares":"LA TAGUA - PUTUMAYO"
  },
  {
    "Lugares":"LA TEBAIDA - QUINDIO"
  },
  {
    "Lugares":"LA TOLA - NARIÑO"
  },
  {
    "Lugares":"LA ULLOA - HUILA"
  },
  {
    "Lugares":"LA UNION - ANTIOQUIA"
  },
  {
    "Lugares":"LA UNION - NARIÑO"
  },
  {
    "Lugares":"LA UNION - VALLE DEL CAUCA"
  },
  {
    "Lugares":"LA UNION - SUCRE"
  },
  {
    "Lugares":"LA URIBE - VALLE DEL CAUCA"
  },
  {
    "Lugares":"LA UVITA - BOYACA"
  },
  {
    "Lugares":"LA VEGA - CUNDINAMARCA"
  },
  {
    "Lugares":"LA VICTORIA - VALLE DEL CAUCA"
  },
  {
    "Lugares":"LA VICTORIA - BOYACA"
  },
  {
    "Lugares":"LA VICTORIA - NARIÑO"
  },
  {
    "Lugares":"LA VIRGINIA - QUINDIO"
  },
  {
    "Lugares":"LA VIRGINIA - RISARALDA"
  },
  {
    "Lugares":"LA YE - CHOCO"
  },
  {
    "Lugares":"LA YE - CORDOBA"
  },
  {
    "Lugares":"LABATECA - NORTE SANTANDER"
  },
  {
    "Lugares":"LABRANZAGRANDE - BOYACA"
  },
  {
    "Lugares":"LANDAZURI - SANTANDER"
  },
  {
    "Lugares":"LARGA - CUNDINAMARCA"
  },
  {
    "Lugares":"LAS ANIMAS - CHOCO"
  },
  {
    "Lugares":"LAS FLORES - GUAJIRA"
  },
  {
    "Lugares":"LAS LAJAS - NARIÑO"
  },
  {
    "Lugares":"LAS MERCEDES - NORTE DE S\/DER."
  },
  {
    "Lugares":"LAS MESAS - NARIÑO"
  },
  {
    "Lugares":"LEBRIJA - SANTANDER"
  },
  {
    "Lugares":"LEIVA - NARIÑO"
  },
  {
    "Lugares":"LEJANIAS - META"
  },
  {
    "Lugares":"LENGUAZAQUE - CUNDINAMARCA"
  },
  {
    "Lugares":"LERIDA - TOLIMA"
  },
  {
    "Lugares":"LIBANO - TOLIMA"
  },
  {
    "Lugares":"LIBORINA - ANTIOQUIA"
  },
  {
    "Lugares":"LINARES - NARIÑO"
  },
  {
    "Lugares":"LLORENTE - NARIÑO"
  },
  {
    "Lugares":"LOBOGUERRERO - VALLE DEL CAUCA"
  },
  {
    "Lugares":"LOMITA ARENA - BOLIVAR"
  },
  {
    "Lugares":"LORICA - CORDOBA"
  },
  {
    "Lugares":"LOS ANDES - NARIÑO"
  },
  {
    "Lugares":"LOS ANGELES - NARIÑO"
  },
  {
    "Lugares":"LOS CERRAJONES - CESAR"
  },
  {
    "Lugares":"LOS CORDOBAS - CORDOBA"
  },
  {
    "Lugares":"LOS GARZONES - CORDOBA"
  },
  {
    "Lugares":"LOS PALMITOS - SUCRE"
  },
  {
    "Lugares":"LOS PATIOS - NORTE SANTANDER"
  },
  {
    "Lugares":"LOS PENDALES - ATLANTICO"
  },
  {
    "Lugares":"LOS ROBLES - CESAR"
  },
  {
    "Lugares":"LOS SANTOS - SANTANDER"
  },
  {
    "Lugares":"LOURDES - NORTE SANTANDER"
  },
  {
    "Lugares":"LURUACO - ATLANTICO"
  },
  {
    "Lugares":"MACANAL - BOYACA"
  },
  {
    "Lugares":"MACARAVITA - SANTANDER"
  },
  {
    "Lugares":"MACEO - ANTIOQUIA"
  },
  {
    "Lugares":"MACHETA - CUNDINAMARCA"
  },
  {
    "Lugares":"MADRID - CUNDINAMARCA"
  },
  {
    "Lugares":"MAGANGUE - BOLIVAR"
  },
  {
    "Lugares":"MAGÜI PAYAN - NARIÑO"
  },
  {
    "Lugares":"MAHATES - BOLIVAR"
  },
  {
    "Lugares":"MAICAO - GUAJIRA"
  },
  {
    "Lugares":"MAJAGUAL - SUCRE"
  },
  {
    "Lugares":"MALAGA - SANTANDER"
  },
  {
    "Lugares":"MALAGANA - BOLIVAR"
  },
  {
    "Lugares":"MALAMBO - ATLANTICO"
  },
  {
    "Lugares":"MALLAMA - NARIÑO"
  },
  {
    "Lugares":"MAMONAL - BOLIVAR"
  },
  {
    "Lugares":"MANATI - ATLANTICO"
  },
  {
    "Lugares":"MANAURE - GUAJIRA"
  },
  {
    "Lugares":"MANAURE BALCON DEL CESAR - CESAR"
  },
  {
    "Lugares":"MANDIVA - CAUCA"
  },
  {
    "Lugares":"MANI - CASANARE"
  },
  {
    "Lugares":"MANIZALES - CALDAS"
  },
  {
    "Lugares":"MANTA - CUNDINAMARCA"
  },
  {
    "Lugares":"MANZANARES - CALDAS"
  },
  {
    "Lugares":"MANZANILLO DEL MAR - BOLIVAR"
  },
  {
    "Lugares":"MAPACHICO ALTO - NARIÑO"
  },
  {
    "Lugares":"MAPACHICO BAJO - NARIÑO"
  },
  {
    "Lugares":"MAPACHICO SAN JOSE - NARIÑO"
  },
  {
    "Lugares":"MARIA LA BAJA - BOLIVAR"
  },
  {
    "Lugares":"MARINILLA - ANTIOQUIA"
  },
  {
    "Lugares":"MARIPI - BOYACA"
  },
  {
    "Lugares":"MARIQUITA - TOLIMA"
  },
  {
    "Lugares":"MARMATO - CALDAS"
  },
  {
    "Lugares":"MARQUETALIA - CALDAS"
  },
  {
    "Lugares":"MARSELLA - RISARALDA"
  },
  {
    "Lugares":"MARULANDA - CALDAS"
  },
  {
    "Lugares":"MATEO GOMEZ - CORDOBA"
  },
  {
    "Lugares":"MEDELLIN - ANTIOQUIA"
  },
  {
    "Lugares":"MEDELLIN DEL ARIARI - META"
  },
  {
    "Lugares":"MEDIA CANOA - VALLE DEL CAUCA"
  },
  {
    "Lugares":"MEDIALUNA - MAGDALENA"
  },
  {
    "Lugares":"MEDINA - CUNDINAMARCA"
  },
  {
    "Lugares":"MELGAR - TOLIMA"
  },
  {
    "Lugares":"MENESES DE HURTADO - NARIÑO"
  },
  {
    "Lugares":"MERCADERES - CAUCA"
  },
  {
    "Lugares":"MESETAS - META"
  },
  {
    "Lugares":"MESITAS DEL COLEGIO - C\/MARCA"
  },
  {
    "Lugares":"MINA EL CERREJON - GUAJIRA"
  },
  {
    "Lugares":"MINA EL HATILLO - CESAR"
  },
  {
    "Lugares":"MINA LA FRANCIA - CESAR"
  },
  {
    "Lugares":"MINCA - MAGDALENA"
  },
  {
    "Lugares":"MINGUEO - GUAJIRA"
  },
  {
    "Lugares":"MIRAFLORES - BOYACA"
  },
  {
    "Lugares":"MIRANDA - CAUCA"
  },
  {
    "Lugares":"MISTRATO - RISARALDA"
  },
  {
    "Lugares":"MOCARI - CORDOBA"
  },
  {
    "Lugares":"MOCOA - PUTUMAYO"
  },
  {
    "Lugares":"MOCONDINO - NARIÑO"
  },
  {
    "Lugares":"MOGOTES - SANTANDER"
  },
  {
    "Lugares":"MOLAGAVITA - SANTANDER"
  },
  {
    "Lugares":"MOMIL - CORDOBA"
  },
  {
    "Lugares":"MOMPOS - BOLIVAR"
  },
  {
    "Lugares":"MONDOMO - CAUCA"
  },
  {
    "Lugares":"MONGUA - BOYACA"
  },
  {
    "Lugares":"MONGUI - BOYACA"
  },
  {
    "Lugares":"MONIQUIRA - BOYACA"
  },
  {
    "Lugares":"MONTE CRISTO - BOLIVAR"
  },
  {
    "Lugares":"MONTEBELLO - ANTIOQUIA"
  },
  {
    "Lugares":"MONTEBELLO \/ CALI - VALLE DEL CAUCA"
  },
  {
    "Lugares":"MONTELIBANO - CORDOBA"
  },
  {
    "Lugares":"MONTENEGRO - QUINDIO"
  },
  {
    "Lugares":"MONTERIA - CORDOBA"
  },
  {
    "Lugares":"MONTERREY - CASANARE"
  },
  {
    "Lugares":"MOÑITOS - CORDOBA"
  },
  {
    "Lugares":"MORALES - BOLIVAR"
  },
  {
    "Lugares":"MORALES - CAUCA"
  },
  {
    "Lugares":"MORCA - BOYACA"
  },
  {
    "Lugares":"MORELIA - CAQUETA"
  },
  {
    "Lugares":"MORICHAL - CASANARE"
  },
  {
    "Lugares":"MORROA - SUCRE"
  },
  {
    "Lugares":"MOSQUERA - CUNDINAMARCA"
  },
  {
    "Lugares":"MOSQUERA - NARIÑO"
  },
  {
    "Lugares":"MOTAVITA - BOYACA"
  },
  {
    "Lugares":"MOTILON - NARIÑO"
  },
  {
    "Lugares":"MULALO \/ YUMBO - VALLE DEL CAUCA"
  },
  {
    "Lugares":"MURILLO - TOLIMA"
  },
  {
    "Lugares":"MUTATA - ANTIOQUIA"
  },
  {
    "Lugares":"MUTISCUA - NORTE SANTANDER"
  },
  {
    "Lugares":"MUZO - BOYACA"
  },
  {
    "Lugares":"NARANJAL - NARIÑO"
  },
  {
    "Lugares":"NARIÑO - ANTIOQUIA"
  },
  {
    "Lugares":"NARIÑO - CUNDINAMARCA"
  },
  {
    "Lugares":"NARIÑO - NARIÑO"
  },
  {
    "Lugares":"NATAGA - HUILA"
  },
  {
    "Lugares":"NATAGAIMA - TOLIMA"
  },
  {
    "Lugares":"NAZARETH - BOYACA"
  },
  {
    "Lugares":"NECOCLI - ANTIOQUIA"
  },
  {
    "Lugares":"NEIRA - CALDAS"
  },
  {
    "Lugares":"NEIVA - HUILA"
  },
  {
    "Lugares":"NEMOCON - CUNDINAMARCA"
  },
  {
    "Lugares":"NILO - CUNDINAMARCA"
  },
  {
    "Lugares":"NIMAIMA - CUNDINAMARCA"
  },
  {
    "Lugares":"NOBSA - BOYACA"
  },
  {
    "Lugares":"NOCAIMA - CUNDINAMARCA"
  },
  {
    "Lugares":"NORCASIA - CALDAS"
  },
  {
    "Lugares":"NOROSI - BOLIVAR"
  },
  {
    "Lugares":"NOVITA - CHOCO"
  },
  {
    "Lugares":"NUEVA COLONIA ZONA URABA - ANT."
  },
  {
    "Lugares":"NUEVA GRANADA - MAGDALENA"
  },
  {
    "Lugares":"NUEVO COLON - BOYACA"
  },
  {
    "Lugares":"NUNCHIA - CASANARE"
  },
  {
    "Lugares":"OBANDO - VALLE DEL CAUCA"
  },
  {
    "Lugares":"OBANDO - NARIÑO"
  },
  {
    "Lugares":"OBONUCO - NARIÑO"
  },
  {
    "Lugares":"OCAMONTE - SANTANDER"
  },
  {
    "Lugares":"OCAÑA - NORTE SANTANDER"
  },
  {
    "Lugares":"OIBA - SANTANDER"
  },
  {
    "Lugares":"OICATA - BOYACA"
  },
  {
    "Lugares":"OLAYA - ANTIOQUIA"
  },
  {
    "Lugares":"OLAYA HERRERA - NARIÑO"
  },
  {
    "Lugares":"OLIVAL - SANTANDER"
  },
  {
    "Lugares":"OPORAPA - HUILA"
  },
  {
    "Lugares":"OREGANAL - GUAJIRA"
  },
  {
    "Lugares":"ORIHUECA - MAGDALENA"
  },
  {
    "Lugares":"ORITO - PUTUMAYO"
  },
  {
    "Lugares":"OROCUE - CASANARE"
  },
  {
    "Lugares":"ORTEGA - TOLIMA"
  },
  {
    "Lugares":"ORTIGAL - CAUCA"
  },
  {
    "Lugares":"OSPINA - NARIÑO"
  },
  {
    "Lugares":"OTANCHE - BOYACA"
  },
  {
    "Lugares":"OVEJAS - SUCRE"
  },
  {
    "Lugares":"PACHAQUIARO - META"
  },
  {
    "Lugares":"PACHAVITA - BOYACA"
  },
  {
    "Lugares":"PACHO - CUNDINAMARCA"
  },
  {
    "Lugares":"PACORA - CALDAS"
  },
  {
    "Lugares":"PADILLA - CAUCA"
  },
  {
    "Lugares":"PADUA - TOLIMA"
  },
  {
    "Lugares":"PAEZ - BOYACA"
  },
  {
    "Lugares":"PAEZ - CAUCA"
  },
  {
    "Lugares":"PAICOL - HUILA"
  },
  {
    "Lugares":"PAILITAS - CESAR"
  },
  {
    "Lugares":"PAIME - CUNDINAMARCA"
  },
  {
    "Lugares":"PAIPA - BOYACA"
  },
  {
    "Lugares":"PAISPAMBA - CAUCA"
  },
  {
    "Lugares":"PAJARITO - BOYACA"
  },
  {
    "Lugares":"PALERMO - MAGDALENA"
  },
  {
    "Lugares":"PALERMO - ANTIOQUIA"
  },
  {
    "Lugares":"PALERMO - HUILA"
  },
  {
    "Lugares":"PALESTINA - CALDAS"
  },
  {
    "Lugares":"PALESTINA - HUILA"
  },
  {
    "Lugares":"PALMA REAL - CALDAS"
  },
  {
    "Lugares":"PALMAR - SANTANDER"
  },
  {
    "Lugares":"PALMAR DE VARELA - ATLANTICO"
  },
  {
    "Lugares":"PALMAS DEL SOCORRO - SANT."
  },
  {
    "Lugares":"PALMAS MONTE CARMELO - CESAR"
  },
  {
    "Lugares":"PALMASECA \/ PALMIRA - VALLE DEL CAUCA"
  },
  {
    "Lugares":"PALMERA CICARARE - CESAR"
  },
  {
    "Lugares":"PALMIRA - VALLE DEL CAUCA"
  },
  {
    "Lugares":"PALMITAS - ANTIOQUIA"
  },
  {
    "Lugares":"PALMITOS - SUCRE"
  },
  {
    "Lugares":"PALOCABILDO - TOLIMA"
  },
  {
    "Lugares":"PALOMINO - GUAJIRA"
  },
  {
    "Lugares":"PAMPLONA - NORTE SANTANDER"
  },
  {
    "Lugares":"PAMPLONITA - NORTE SANTANDER"
  },
  {
    "Lugares":"PANCE \/ CALI - VALLE DEL CAUCA"
  },
  {
    "Lugares":"PANDI - CUNDINAMARCA"
  },
  {
    "Lugares":"PANQUEBA - BOYACA"
  },
  {
    "Lugares":"PAPAYAL - GUAJIRA"
  },
  {
    "Lugares":"PARAMO - SANTANDER"
  },
  {
    "Lugares":"PARATEBUENO - CUNDINAMARCA"
  },
  {
    "Lugares":"PASACABALLOS - BOLIVAR"
  },
  {
    "Lugares":"PASCA - CUNDINAMARCA"
  },
  {
    "Lugares":"PASIZARA - NARIÑO"
  },
  {
    "Lugares":"PASTO - NARIÑO"
  },
  {
    "Lugares":"PATIA - CAUCA"
  },
  {
    "Lugares":"PAUNA - BOYACA"
  },
  {
    "Lugares":"PAVAS - VALLE DEL CAUCA"
  },
  {
    "Lugares":"PAYA - BOYACA"
  },
  {
    "Lugares":"PAYANDE - TOLIMA"
  },
  {
    "Lugares":"PAZ DE ARIPORO - CASANARE"
  },
  {
    "Lugares":"PAZ DE RIO - BOYACA"
  },
  {
    "Lugares":"PEDRAZA - MAGDALENA"
  },
  {
    "Lugares":"PEDREGAL - NARIÑO"
  },
  {
    "Lugares":"PEDREGAL - CAUCA"
  },
  {
    "Lugares":"PEJENDINO REYES - NARIÑO"
  },
  {
    "Lugares":"PELAYA - CESAR"
  },
  {
    "Lugares":"PENSILVANIA - CALDAS"
  },
  {
    "Lugares":"PEQUE - ANTIOQUIA"
  },
  {
    "Lugares":"PEREIRA - RISARALDA"
  },
  {
    "Lugares":"PERICO AGUAO - MAGDALENA"
  },
  {
    "Lugares":"PESCA - BOYACA"
  },
  {
    "Lugares":"PESCADERO - SANTANDER"
  },
  {
    "Lugares":"PESCADOR - CAUCA"
  },
  {
    "Lugares":"PICALEÑA - TOLIMA"
  },
  {
    "Lugares":"PIE DE CUESTA - SANTANDER"
  },
  {
    "Lugares":"PIEDRA ANCHA - NARIÑO"
  },
  {
    "Lugares":"PIEDRA SENTADA - CAUCA"
  },
  {
    "Lugares":"PIEDRAS - TOLIMA"
  },
  {
    "Lugares":"PIENDAMO - CAUCA"
  },
  {
    "Lugares":"PIJAO - QUINDIO"
  },
  {
    "Lugares":"PILCUAN - NARIÑO"
  },
  {
    "Lugares":"PINAR DEL RIO - ATLANTICO"
  },
  {
    "Lugares":"PINCHOTE - SANTANDER"
  },
  {
    "Lugares":"PIOJO - ATLANTICO"
  },
  {
    "Lugares":"PISBA - BOYACA"
  },
  {
    "Lugares":"PITAL - HUILA"
  },
  {
    "Lugares":"PITAL DE MEGUA - ATLANTICO"
  },
  {
    "Lugares":"PITALITO - HUILA"
  },
  {
    "Lugares":"PIVIJAY - MAGDALENA"
  },
  {
    "Lugares":"PLANADAS - TOLIMA"
  },
  {
    "Lugares":"PLANETA RICA - CORDOBA"
  },
  {
    "Lugares":"PLANTA CAMPOLLO GAMBOTE - BOL."
  },
  {
    "Lugares":"PLANTA CEMEX CARACOLITO \/ PAYANDE - TOL."
  },
  {
    "Lugares":"PLATEADO - CAUCA"
  },
  {
    "Lugares":"PLATO - MAGDALENA"
  },
  {
    "Lugares":"PLAYA RICA - TOLIMA"
  },
  {
    "Lugares":"POLICARPA - NARIÑO"
  },
  {
    "Lugares":"POLONUEVO - ATLANTICO"
  },
  {
    "Lugares":"POMPEYA - META"
  },
  {
    "Lugares":"PONEDERA - ATLANTICO"
  },
  {
    "Lugares":"PONTEZUELA - BOLIVAR"
  },
  {
    "Lugares":"POPAYAN - CAUCA"
  },
  {
    "Lugares":"POPONTE - CESAR"
  },
  {
    "Lugares":"PORE - CASANARE"
  },
  {
    "Lugares":"POTOSI - NARIÑO"
  },
  {
    "Lugares":"POTRERITO - JAMUNDI - VALLE DEL CAUCA"
  },
  {
    "Lugares":"POZO CARICARE - ARAUCA"
  },
  {
    "Lugares":"PRADERA - VALLE DEL CAUCA"
  },
  {
    "Lugares":"PRADO - TOLIMA"
  },
  {
    "Lugares":"PRESIDENTE - VALLE DEL CAUCA"
  },
  {
    "Lugares":"PROVIDENCIA - NARIÑO"
  },
  {
    "Lugares":"PUEBLITO LOS ANDES - MAG."
  },
  {
    "Lugares":"PUEBLO BELLO - CESAR"
  },
  {
    "Lugares":"PUEBLO NUEVO - CORDOBA"
  },
  {
    "Lugares":"PUEBLO NUEVO - MAGDALENA"
  },
  {
    "Lugares":"PUEBLO RICO - RISARALDA"
  },
  {
    "Lugares":"PUEBLO TAPADO - QUINDIO"
  },
  {
    "Lugares":"PUEBLO VIEJO - MAGDALENA"
  },
  {
    "Lugares":"PUEBLORRICO - ANTIOQUIA"
  },
  {
    "Lugares":"PUENTE BOYACA - BOYACA"
  },
  {
    "Lugares":"PUENTE DE PIEDRA - CUND."
  },
  {
    "Lugares":"PUENTE NACIONAL - SANTANDER"
  },
  {
    "Lugares":"PUENTE SOGAMOSO - SANTANDER"
  },
  {
    "Lugares":"PUERRES - NARIÑO"
  },
  {
    "Lugares":"PUERTO ARAUJO - SANTANDER"
  },
  {
    "Lugares":"PUERTO ASIS - PUTUMAYO"
  },
  {
    "Lugares":"PUERTO BAHIA BARU - BOLIVAR"
  },
  {
    "Lugares":"PUERTO BERRIO - ANTIOQUIA"
  },
  {
    "Lugares":"PUERTO BOGOTA - CUNDINAMARCA"
  },
  {
    "Lugares":"PUERTO BOYACA - BOYACA"
  },
  {
    "Lugares":"PUERTO BOYACA - ANTIOQUIA"
  },
  {
    "Lugares":"PUERTO BRISA - GUAJIRA"
  },
  {
    "Lugares":"PUERTO CAICEDO - PUTUMAYO"
  },
  {
    "Lugares":"PUERTO COLOMBIA - ATLANTICO"
  },
  {
    "Lugares":"PUERTO CONCORDIA - META"
  },
  {
    "Lugares":"PUERTO ESCONDIDO - CORDOBA"
  },
  {
    "Lugares":"PUERTO GAITAN - META"
  },
  {
    "Lugares":"PUERTO GIRALDO - ATLANTICO"
  },
  {
    "Lugares":"PUERTO GUZMAN - PUTUMAYO"
  },
  {
    "Lugares":"PUERTO LEGUIZAMO - PUTUMAYO"
  },
  {
    "Lugares":"PUERTO LIBERTADOR - CORDOBA"
  },
  {
    "Lugares":"PUERTO LLERAS - META"
  },
  {
    "Lugares":"PUERTO LOPEZ - META"
  },
  {
    "Lugares":"PUERTO NARE - ANTIOQUIA"
  },
  {
    "Lugares":"PUERTO NUEVO - MAGDALENA"
  },
  {
    "Lugares":"PUERTO PARRA - SANTANDER"
  },
  {
    "Lugares":"PUERTO RICO - BOLIVAR"
  },
  {
    "Lugares":"PUERTO RICO - CAQUETA"
  },
  {
    "Lugares":"PUERTO RICO - META"
  },
  {
    "Lugares":"PUERTO RONDON - ARAUCA"
  },
  {
    "Lugares":"PUERTO SALGAR - CUNDINAMARCA"
  },
  {
    "Lugares":"PUERTO SANTANDER - NORTE SANT."
  },
  {
    "Lugares":"PUERTO TEJADA - CAUCA"
  },
  {
    "Lugares":"PUERTO TRIUNFO - ANTIOQUIA"
  },
  {
    "Lugares":"PUERTO VALDIVIA - ANTIOQUIA"
  },
  {
    "Lugares":"PUERTO WILCHES - SANTANDER"
  },
  {
    "Lugares":"PULI - CUNDINAMARCA"
  },
  {
    "Lugares":"PUNTA BRAVA - META"
  },
  {
    "Lugares":"PUNTA CANOA - BOLIVAR"
  },
  {
    "Lugares":"PUPIALES - NARIÑO"
  },
  {
    "Lugares":"PURACE - CAUCA"
  },
  {
    "Lugares":"PURIFICACION - TOLIMA"
  },
  {
    "Lugares":"PURISIMA - CORDOBA"
  },
  {
    "Lugares":"QUETAME - CUNDINAMARCA"
  },
  {
    "Lugares":"QUIBDO - CHOCO"
  },
  {
    "Lugares":"QUIMBAYA - QUINDIO"
  },
  {
    "Lugares":"QUINCHIA - RISARALDA"
  },
  {
    "Lugares":"QUIPAMA - BOYACA"
  },
  {
    "Lugares":"QUIPILE - CUNDINAMARCA"
  },
  {
    "Lugares":"RAGONVALIA - NORTE SANTANDER"
  },
  {
    "Lugares":"RAMIRIQUI - BOYACA"
  },
  {
    "Lugares":"RAQUIRA - BOYACA"
  },
  {
    "Lugares":"RECETOR - CASANARE"
  },
  {
    "Lugares":"REGIDOR - BOLIVAR"
  },
  {
    "Lugares":"REMEDIOS - ANTIOQUIA"
  },
  {
    "Lugares":"REPELON - ATLANTICO"
  },
  {
    "Lugares":"RESTREPO - META"
  },
  {
    "Lugares":"RESTREPO - VALLE DEL CAUCA"
  },
  {
    "Lugares":"RETIRO DE LOS INDIOS - CORDOBA"
  },
  {
    "Lugares":"RETIRO NUEVO - BOLIVAR"
  },
  {
    "Lugares":"RICAURTE - CUNDINAMARCA"
  },
  {
    "Lugares":"RICAURTE - NARIÑO"
  },
  {
    "Lugares":"RINCON HONDO - CESAR"
  },
  {
    "Lugares":"RIO BLANCO - CAUCA"
  },
  {
    "Lugares":"RIO DE ORO - CESAR"
  },
  {
    "Lugares":"RIO VIEJO - BOLIVAR"
  },
  {
    "Lugares":"RIOANCHO - GUAJIRA"
  },
  {
    "Lugares":"RIOBLANCO - TOLIMA"
  },
  {
    "Lugares":"RIOFRIO - MAGDALENA"
  },
  {
    "Lugares":"RIOFRIO - VALLE DEL CAUCA"
  },
  {
    "Lugares":"RIOHACHA - GUAJIRA"
  },
  {
    "Lugares":"RIONEGRO - ANTIOQUIA"
  },
  {
    "Lugares":"RIONEGRO - SANTANDER"
  },
  {
    "Lugares":"RIOSUCIO - CALDAS"
  },
  {
    "Lugares":"RISARALDA - CALDAS"
  },
  {
    "Lugares":"RIVERA - HUILA"
  },
  {
    "Lugares":"ROBERTO PAYAN - NARIÑO"
  },
  {
    "Lugares":"ROLDANILLO - VALLE DEL CAUCA"
  },
  {
    "Lugares":"RONCESVALLE DEL CAUCAS - TOLIMA"
  },
  {
    "Lugares":"RONDON - BOYACA"
  },
  {
    "Lugares":"ROSAS - CAUCA"
  },
  {
    "Lugares":"ROVIRA - TOLIMA"
  },
  {
    "Lugares":"ROZO - VALLE DEL CAUCA"
  },
  {
    "Lugares":"SABANA DE TORRES - SANTANDER"
  },
  {
    "Lugares":"SABANAGRANDE - ATLANTICO"
  },
  {
    "Lugares":"SABANALARGA - ANTIOQUIA"
  },
  {
    "Lugares":"SABANALARGA - ATLANTICO"
  },
  {
    "Lugares":"SABANALARGA - CASANARE"
  },
  {
    "Lugares":"SABANETA - ANTIOQUIA"
  },
  {
    "Lugares":"SABOYA - BOYACA"
  },
  {
    "Lugares":"SACAMA - CASANARE"
  },
  {
    "Lugares":"SACHICA - BOYACA"
  },
  {
    "Lugares":"SAHAGUN - CORDOBA"
  },
  {
    "Lugares":"SALADOBLANCO - HUILA"
  },
  {
    "Lugares":"SALAHONDA - NARIÑO"
  },
  {
    "Lugares":"SALAMINA - CALDAS"
  },
  {
    "Lugares":"SALAMINA - MAGDALENA"
  },
  {
    "Lugares":"SALAZAR - NORTE SANTANDER"
  },
  {
    "Lugares":"SALDAÑA - TOLIMA"
  },
  {
    "Lugares":"SALENTO - QUINDIO"
  },
  {
    "Lugares":"SALGAR - ATLANTICO"
  },
  {
    "Lugares":"SALGAR - ANTIOQUIA"
  },
  {
    "Lugares":"SAMACA - BOYACA"
  },
  {
    "Lugares":"SAMANA - CALDAS"
  },
  {
    "Lugares":"SAMANIEGO - NARIÑO"
  },
  {
    "Lugares":"SAMARIA - CALDAS"
  },
  {
    "Lugares":"SAMPUES - SUCRE"
  },
  {
    "Lugares":"SAN AGUSTIN - HUILA"
  },
  {
    "Lugares":"SAN ALBERTO - CESAR"
  },
  {
    "Lugares":"SAN ANDRES - SANTANDER"
  },
  {
    "Lugares":"SAN ANDRES DE CUERQUIA - ANTIOQUIA"
  },
  {
    "Lugares":"SAN ANDRES DE SOTAVENTO - CORDOBA"
  },
  {
    "Lugares":"SAN ANGEL - MAGDALENA"
  },
  {
    "Lugares":"SAN ANTERO - CORDOBA"
  },
  {
    "Lugares":"SAN ANTONIO - TOLIMA"
  },
  {
    "Lugares":"SAN ANTONIO DE ARANDA - NARIÑO"
  },
  {
    "Lugares":"SAN ANTONIO DE PEREIRA - ANTIOQUIA"
  },
  {
    "Lugares":"SAN ANTONIO DE PRADO - ANTIOQUIA"
  },
  {
    "Lugares":"SAN ANTONIO DEL TEQUENDAMA - C\/MARCA"
  },
  {
    "Lugares":"SAN BASILIO DEL PALENQUE - BOLIVAR"
  },
  {
    "Lugares":"SAN BENITO - SANTANDER"
  },
  {
    "Lugares":"SAN BENITO - SUCRE"
  },
  {
    "Lugares":"SAN BERNARDO - CUNDINAMARCA"
  },
  {
    "Lugares":"SAN BERNARDO - NARIÑO"
  },
  {
    "Lugares":"SAN BERNARDO DEL VIENTO - CORDOBA"
  },
  {
    "Lugares":"SAN CALIXTO - NORTE SANTANDER"
  },
  {
    "Lugares":"SAN CARLOS - ANTIOQUIA"
  },
  {
    "Lugares":"SAN CAYETANO - BOLIVAR"
  },
  {
    "Lugares":"SAN CAYETANO - CUNDINAMARCA"
  },
  {
    "Lugares":"SAN CAYETANO - NORTE SANTANDER"
  },
  {
    "Lugares":"SAN CLEMENTE - RISARALDA"
  },
  {
    "Lugares":"SAN CRISTOBAL - ANTIOQUIA"
  },
  {
    "Lugares":"SAN CRISTOBAL - BOLIVAR"
  },
  {
    "Lugares":"SAN DIEGO - CESAR"
  },
  {
    "Lugares":"SAN EDUARDO - BOYACA"
  },
  {
    "Lugares":"SAN ESTANISLAO - ARENAL - BOLIVAR"
  },
  {
    "Lugares":"SAN FAUSTINO - NORTE SANTANDER"
  },
  {
    "Lugares":"SAN FELIPE - TOLIMA"
  },
  {
    "Lugares":"SAN FELIX - CALDAS"
  },
  {
    "Lugares":"SAN FERNANDO - NARIÑO"
  },
  {
    "Lugares":"SAN FRANCISCO - NARIÑO"
  },
  {
    "Lugares":"SAN FRANCISCO - ANTIOQUIA"
  },
  {
    "Lugares":"SAN FRANCISCO - CUNDINAMARCA"
  },
  {
    "Lugares":"SAN FRANCISCO - PUTUMAYO"
  },
  {
    "Lugares":"SAN GIL - SANTANDER"
  },
  {
    "Lugares":"SAN JERONIMO - ANTIOQUIA"
  },
  {
    "Lugares":"SAN JOSE - CALDAS"
  },
  {
    "Lugares":"SAN JOSE - NARIÑO"
  },
  {
    "Lugares":"SAN JOSE DE ALBAN - NARIÑO"
  },
  {
    "Lugares":"SAN JOSE DE COAPITAS - NARIÑO"
  },
  {
    "Lugares":"SAN JOSE DE CORDOBA - NARIÑO"
  },
  {
    "Lugares":"SAN JOSE DE LA MONTAÑA - ANTIOQUIA"
  },
  {
    "Lugares":"SAN JOSE DE MIRANDA - SANTANDER"
  },
  {
    "Lugares":"SAN JOSE DE PARE - BOYACA"
  },
  {
    "Lugares":"SAN JOSE DE URE - CORDOBA"
  },
  {
    "Lugares":"SAN JOSE DEL FRAGUA - CAQUETA"
  },
  {
    "Lugares":"SAN JOSE DEL GUAVIARE - GUAVIARE"
  },
  {
    "Lugares":"SAN JOSE DEL NUS - ANTIOQUIA"
  },
  {
    "Lugares":"SAN JOSE DEL ORIENTE - CESAR"
  },
  {
    "Lugares":"SAN JUAN - NARIÑO"
  },
  {
    "Lugares":"SAN JUAN ANGANOY - NARIÑO"
  },
  {
    "Lugares":"SAN JUAN DE ARAMA - META"
  },
  {
    "Lugares":"SAN JUAN DE RIO SECO - CUND."
  },
  {
    "Lugares":"SAN JUAN DE SUMAPAZ - CUND."
  },
  {
    "Lugares":"SAN JUAN DE URABA - ANTIOQUIA"
  },
  {
    "Lugares":"SAN JUAN DEL CESAR - GUAJIRA"
  },
  {
    "Lugares":"SAN JUAN NEPOMUCENO - BOL."
  },
  {
    "Lugares":"SAN LORENZO - NARIÑO"
  },
  {
    "Lugares":"SAN LUIS - ANTIOQUIA"
  },
  {
    "Lugares":"SAN LUIS - TOLIMA"
  },
  {
    "Lugares":"SAN LUIS DE GACENO - BOYACA"
  },
  {
    "Lugares":"SAN LUIS DE PALENQUE - CASANARE"
  },
  {
    "Lugares":"SAN MARCOS - SUCRE"
  },
  {
    "Lugares":"SAN MARCOS - VALLE DEL CAUCA"
  },
  {
    "Lugares":"SAN MARTIN - CESAR"
  },
  {
    "Lugares":"SAN MARTIN - META"
  },
  {
    "Lugares":"SAN MARTIN - BOLIVAR"
  },
  {
    "Lugares":"SAN MATEO - BOYACA"
  },
  {
    "Lugares":"SAN MIGUEL - PUTUMAYO"
  },
  {
    "Lugares":"SAN MIGUEL DE SEMA - BOYACA"
  },
  {
    "Lugares":"SAN ONOFRE - SUCRE"
  },
  {
    "Lugares":"SAN PABLO - BOLIVAR"
  },
  {
    "Lugares":"SAN PABLO - NARIÑO"
  },
  {
    "Lugares":"SAN PABLO DE BORBUR - BOYACA"
  },
  {
    "Lugares":"SAN PEDRO - SUCRE"
  },
  {
    "Lugares":"SAN PEDRO - VALLE DEL CAUCA"
  },
  {
    "Lugares":"SAN PEDRO DE CARTAGO - NARIÑO"
  },
  {
    "Lugares":"SAN PEDRO DE IGÜAQUE - BOYACA"
  },
  {
    "Lugares":"SAN PEDRO DE LOS MILAGROS - ANT"
  },
  {
    "Lugares":"SAN PEDRO DE URABA - ANTIOQUIA"
  },
  {
    "Lugares":"SAN PELAYO - CORDOBA"
  },
  {
    "Lugares":"SAN RAFAEL - ANTIOQUIA"
  },
  {
    "Lugares":"SAN ROQUE - ANTIOQUIA"
  },
  {
    "Lugares":"SAN ROQUE - CESAR"
  },
  {
    "Lugares":"SAN SEBASTIAN - CAUCA"
  },
  {
    "Lugares":"SAN SEBASTIAN - MAGDALENA"
  },
  {
    "Lugares":"SAN VICENTE - ANTIOQUIA"
  },
  {
    "Lugares":"SAN VICENTE DE CHUCURI - SANTANDER"
  },
  {
    "Lugares":"SAN VICENTE DEL CAGUAN - CAQUETA"
  },
  {
    "Lugares":"SANDONA - NARIÑO"
  },
  {
    "Lugares":"SANTA ANA - BOLIVAR"
  },
  {
    "Lugares":"SANTA ANA - MAGDALENA"
  },
  {
    "Lugares":"SANTA BARBARA - ANTIOQUIA"
  },
  {
    "Lugares":"SANTA BARBARA - SANTANDER"
  },
  {
    "Lugares":"SANTA BARBARA DE ISCUANDE - NARIÑO "
  },
  {
    "Lugares":"SANTA CATALINA - BOLIVAR"
  },
  {
    "Lugares":"SANTA ELENA - ANTIOQUIA"
  },
  {
    "Lugares":"SANTA ELENA \/ PALMIRA - VALLE DEL CAUCA"
  },
  {
    "Lugares":"SANTA ISABEL - ANTIOQUIA"
  },
  {
    "Lugares":"SANTA ISABEL - TOLIMA"
  },
  {
    "Lugares":"SANTA LUCIA - ATLANTICO"
  },
  {
    "Lugares":"SANTA MARIA - BOYACA"
  },
  {
    "Lugares":"SANTA MARIA - HUILA"
  },
  {
    "Lugares":"SANTA MARTA - MAGDALENA"
  },
  {
    "Lugares":"SANTA ROSA DE CABAL - RISARALDA"
  },
  {
    "Lugares":"SANTA ROSA DE LIMA - BOLIVAR"
  },
  {
    "Lugares":"SANTA ROSA DE OSOS - ANTIOQUIA"
  },
  {
    "Lugares":"SANTA ROSA DE VITERBO - BOYACA"
  },
  {
    "Lugares":"SANTA ROSA DEL SUR - BOLIVAR"
  },
  {
    "Lugares":"SANTA SOFIA - BOYACA"
  },
  {
    "Lugares":"SANTA VERONICA - ATLANTICO"
  },
  {
    "Lugares":"SANTACRUZ GUACHAVEZ - NARIÑO"
  },
  {
    "Lugares":"SANTAFE DE ANTIOQUIA - ANTIOQUIA"
  },
  {
    "Lugares":"SANTAGUEDA - CALDAS"
  },
  {
    "Lugares":"SANTANA - BOYACA"
  },
  {
    "Lugares":"SANTANDER DE QUILICHAO - CAUCA"
  },
  {
    "Lugares":"SANTANDERCITO - CUNDINAMARCA"
  },
  {
    "Lugares":"SANTIAGO - NORTE SANTANDER"
  },
  {
    "Lugares":"SANTIAGO - PUTUMAYO"
  },
  {
    "Lugares":"SANTO DOMINGO - ANTIOQUIA"
  },
  {
    "Lugares":"SANTO TOMAS - ATLANTICO"
  },
  {
    "Lugares":"SANTUARIO - ANTIOQUIA"
  },
  {
    "Lugares":"SANTUARIO - RISARALDA"
  },
  {
    "Lugares":"SAPUYES - NARIÑO"
  },
  {
    "Lugares":"SARAVENA - ARAUCA"
  },
  {
    "Lugares":"SARDINATA - NORTE SANTANDER"
  },
  {
    "Lugares":"SASAIMA - CUNDINAMARCA"
  },
  {
    "Lugares":"SATIVANORTE - BOYACA"
  },
  {
    "Lugares":"SATIVASUR - BOYACA"
  },
  {
    "Lugares":"SEGOVIA - ANTIOQUIA"
  },
  {
    "Lugares":"SESQUILE - CUNDINAMARCA"
  },
  {
    "Lugares":"SEVILLA - VALLE DEL CAUCA"
  },
  {
    "Lugares":"SEVILLA - ANTIOQUIA"
  },
  {
    "Lugares":"SEVILLA ZONA BANANERA - MAG"
  },
  {
    "Lugares":"SIACHOQUE - BOYACA"
  },
  {
    "Lugares":"SIBARCO - ATLANTICO"
  },
  {
    "Lugares":"SIBATE - CUNDINAMARCA"
  },
  {
    "Lugares":"SIBUNDOY - PUTUMAYO"
  },
  {
    "Lugares":"SILOS - NORTE SANTANDER"
  },
  {
    "Lugares":"SILVANIA - CUNDINAMARCA"
  },
  {
    "Lugares":"SILVIA - CAUCA"
  },
  {
    "Lugares":"SIMACOTA - SANTANDER"
  },
  {
    "Lugares":"SIMIJACA - CUNDINAMARCA"
  },
  {
    "Lugares":"SIMITI - BOLIVAR"
  },
  {
    "Lugares":"SINCE - SUCRE"
  },
  {
    "Lugares":"SINCELEJO - SUCRE"
  },
  {
    "Lugares":"SINCERIN - BOLIVAR"
  },
  {
    "Lugares":"SITIO NUEVO - MAGDALENA"
  },
  {
    "Lugares":"SOACHA - CUNDINAMARCA"
  },
  {
    "Lugares":"SOATA - BOYACA"
  },
  {
    "Lugares":"SOCHA - BOYACA"
  },
  {
    "Lugares":"SOCORRO - SANTANDER"
  },
  {
    "Lugares":"SOCOTA - BOYACA"
  },
  {
    "Lugares":"SOGAMOSO - BOYACA"
  },
  {
    "Lugares":"SOLEDAD - ATLANTICO"
  },
  {
    "Lugares":"SOMONDOCO - BOYACA"
  },
  {
    "Lugares":"SONSO - VALLE DEL CAUCA"
  },
  {
    "Lugares":"SONSON - ANTIOQUIA"
  },
  {
    "Lugares":"SOPETRAN - ANTIOQUIA"
  },
  {
    "Lugares":"SOPLAVIENTO - BOLIVAR"
  },
  {
    "Lugares":"SOPO - CUNDINAMARCA"
  },
  {
    "Lugares":"SORA - BOYACA"
  },
  {
    "Lugares":"SORACA - BOYACA"
  },
  {
    "Lugares":"SOTAQUIRA - BOYACA"
  },
  {
    "Lugares":"SOTARA - CAUCA"
  },
  {
    "Lugares":"SOTOMAYOR - NARIÑO"
  },
  {
    "Lugares":"SUAITA - SANTANDER"
  },
  {
    "Lugares":"SUAN - ATLANTICO"
  },
  {
    "Lugares":"SUAREZ - CAUCA"
  },
  {
    "Lugares":"SUAREZ - TOLIMA"
  },
  {
    "Lugares":"SUAZA - HUILA"
  },
  {
    "Lugares":"SUBACHOQUE - CUNDINAMARCA"
  },
  {
    "Lugares":"SUBIA - CUNDINAMARCA"
  },
  {
    "Lugares":"SUCRE - SANTANDER"
  },
  {
    "Lugares":"SUCUMBIOS - NARIÑO"
  },
  {
    "Lugares":"SUESCA - CUNDINAMARCA"
  },
  {
    "Lugares":"SUPATA - CUNDINAMARCA"
  },
  {
    "Lugares":"SUPIA - CALDAS"
  },
  {
    "Lugares":"SUSA - CUNDINAMARCA"
  },
  {
    "Lugares":"SUSACON - BOYACA"
  },
  {
    "Lugares":"SUTAMARCHAN - BOYACA"
  },
  {
    "Lugares":"SUTATAUSA - CUNDINAMARCA"
  },
  {
    "Lugares":"SUTATENZA - BOYACA"
  },
  {
    "Lugares":"TABIO - CUNDINAMARCA"
  },
  {
    "Lugares":"TABLON DE GOMEZ - NARIÑO"
  },
  {
    "Lugares":"TABLONES \/ PALMIRA - VALLE DEL CAUCA"
  },
  {
    "Lugares":"TADO - CHOCO"
  },
  {
    "Lugares":"TAGANGA - MAGDALENA"
  },
  {
    "Lugares":"TALAIGUA - BOLIVAR"
  },
  {
    "Lugares":"TAMALAMEQUE - CESAR"
  },
  {
    "Lugares":"TAMARA - CASANARE"
  },
  {
    "Lugares":"TAME - ARAUCA"
  },
  {
    "Lugares":"TAMESIS - ANTIOQUIA"
  },
  {
    "Lugares":"TAMINANGO - NARIÑO"
  },
  {
    "Lugares":"TANGUA - NARIÑO"
  },
  {
    "Lugares":"TARAZA - ANTIOQUIA"
  },
  {
    "Lugares":"TARQUI - HUILA"
  },
  {
    "Lugares":"TARSO - ANTIOQUIA"
  },
  {
    "Lugares":"TASCO - BOYACA"
  },
  {
    "Lugares":"TAURAMENA - CASANARE"
  },
  {
    "Lugares":"TAUSA - CUNDINAMARCA"
  },
  {
    "Lugares":"TELLO - HUILA"
  },
  {
    "Lugares":"TENA - CUNDINAMARCA"
  },
  {
    "Lugares":"TENERIFE - MAGDALENA"
  },
  {
    "Lugares":"TENJO - CUNDINAMARCA"
  },
  {
    "Lugares":"TENZA - BOYACA"
  },
  {
    "Lugares":"TEORAMA - NORTE SANTANDER"
  },
  {
    "Lugares":"TERUEL - HUILA"
  },
  {
    "Lugares":"TESALIA - HUILA"
  },
  {
    "Lugares":"TESCUAL - NARIÑO"
  },
  {
    "Lugares":"TIBACUY - CUNDINAMARCA"
  },
  {
    "Lugares":"TIBANA - BOYACA"
  },
  {
    "Lugares":"TIBAQUI - CUNDINAMARCA"
  },
  {
    "Lugares":"TIBASOSA - BOYACA"
  },
  {
    "Lugares":"TIBIRITA - CUNDINAMARCA"
  },
  {
    "Lugares":"TIBU - NORTE SANTANDER"
  },
  {
    "Lugares":"TIENDA NUEVA - VALLE DEL CAUCA"
  },
  {
    "Lugares":"TIERRA ALTA - CORDOBA"
  },
  {
    "Lugares":"TIERRANEGRA - BOYACA"
  },
  {
    "Lugares":"TIMANA - HUILA"
  },
  {
    "Lugares":"TIMBA - CAUCA"
  },
  {
    "Lugares":"TIMBIO - CAUCA"
  },
  {
    "Lugares":"TINJACA - BOYACA"
  },
  {
    "Lugares":"TIPACOQUE - BOYACA"
  },
  {
    "Lugares":"TIQUISIO - BOLIVAR"
  },
  {
    "Lugares":"TITIRIBI - ANTIOQUIA"
  },
  {
    "Lugares":"TOCA - BOYACA"
  },
  {
    "Lugares":"TOCAIMA - CUNDINAMARCA"
  },
  {
    "Lugares":"TOCANCIPA - CUNDINAMARCA"
  },
  {
    "Lugares":"TOGÜI - BOYACA"
  },
  {
    "Lugares":"TOLEDO - ANTIOQUIA"
  },
  {
    "Lugares":"TOLEDO - NORTE SANTANDER"
  },
  {
    "Lugares":"TOLEMAIDA - TOLIMA"
  },
  {
    "Lugares":"TOLU - SUCRE"
  },
  {
    "Lugares":"TOLUVIEJO - SUCRE"
  },
  {
    "Lugares":"TOPAGA - BOYACA"
  },
  {
    "Lugares":"TOPAIPI - CUNDINAMARCA"
  },
  {
    "Lugares":"TORIBIO - CAUCA"
  },
  {
    "Lugares":"TORO - VALLE DEL CAUCA"
  },
  {
    "Lugares":"TOTA - BOYACA"
  },
  {
    "Lugares":"TOTORO - CAUCA"
  },
  {
    "Lugares":"TRINIDAD - CASANARE"
  },
  {
    "Lugares":"TRUJILLO - VALLE DEL CAUCA"
  },
  {
    "Lugares":"TUBARA - ATLANTICO"
  },
  {
    "Lugares":"TUCHIN - CORDOBA"
  },
  {
    "Lugares":"TUCURINCA - MAGDALENA"
  },
  {
    "Lugares":"TULUA - VALLE DEL CAUCA"
  },
  {
    "Lugares":"TUMACO - NARIÑO"
  },
  {
    "Lugares":"TUNIA - CAUCA"
  },
  {
    "Lugares":"TUNJA - BOYACA"
  },
  {
    "Lugares":"TUNUNGUA - BOYACA"
  },
  {
    "Lugares":"TUQUERRES - NARIÑO"
  },
  {
    "Lugares":"TURBACO - BOLIVAR"
  },
  {
    "Lugares":"TURBANA - BOLIVAR"
  },
  {
    "Lugares":"TURBO - ANTIOQUIA"
  },
  {
    "Lugares":"TURMEQUE - BOYACA"
  },
  {
    "Lugares":"TUTA - BOYACA"
  },
  {
    "Lugares":"TUTAZA - BOYACA"
  },
  {
    "Lugares":"TUTUNENDO - CHOCO"
  },
  {
    "Lugares":"UBALA - CUNDINAMARCA"
  },
  {
    "Lugares":"UBAQUE - CUNDINAMARCA"
  },
  {
    "Lugares":"UBATE - CUNDINAMARCA"
  },
  {
    "Lugares":"ULLOA - VALLE DEL CAUCA"
  },
  {
    "Lugares":"UMBITA - BOYACA"
  },
  {
    "Lugares":"UNE - CUNDINAMARCA"
  },
  {
    "Lugares":"UNION PANAMERICANA - CHOCO"
  },
  {
    "Lugares":"URIBIA - GUAJIRA"
  },
  {
    "Lugares":"URRAO - ANTIOQUIA"
  },
  {
    "Lugares":"URUMITA - GUAJIRA"
  },
  {
    "Lugares":"USIACURI - ATLANTICO"
  },
  {
    "Lugares":"USME - CUNDINAMARCA"
  },
  {
    "Lugares":"UTICA - CUNDINAMARCA"
  },
  {
    "Lugares":"VADO REAL - SANTANDER"
  },
  {
    "Lugares":"VALDIVIA - ANTIOQUIA"
  },
  {
    "Lugares":"VALENCIA - CORDOBA"
  },
  {
    "Lugares":"VALENCIA DE JESUS - CESAR"
  },
  {
    "Lugares":"VALLE DE SAN JOSE - SANTANDER"
  },
  {
    "Lugares":"VALLE DE SAN JUAN - TOLIMA"
  },
  {
    "Lugares":"VALLE DEL GUAMUEZ - PUTUMAYO"
  },
  {
    "Lugares":"VALLEDUPAR - CESAR"
  },
  {
    "Lugares":"VALPARAISO - ANTIOQUIA"
  },
  {
    "Lugares":"VEGACHI - ANTIOQUIA"
  },
  {
    "Lugares":"VELEZ - SANTANDER"
  },
  {
    "Lugares":"VENADILLO - TOLIMA"
  },
  {
    "Lugares":"VENECIA - ANTIOQUIA"
  },
  {
    "Lugares":"VENECIA - CUNDINAMARCA"
  },
  {
    "Lugares":"VENTAQUEMADA - BOYACA"
  },
  {
    "Lugares":"VERGARA - CUNDINAMARCA"
  },
  {
    "Lugares":"VERSALLES - ANTIOQUIA"
  },
  {
    "Lugares":"VERSALLES - VALLE DEL CAUCA"
  },
  {
    "Lugares":"VIANI - CUNDINAMARCA"
  },
  {
    "Lugares":"VICTORIA - CALDAS"
  },
  {
    "Lugares":"VIJES - VALLE DEL CAUCA"
  },
  {
    "Lugares":"VILLA CARO - NORTE SANTANDER"
  },
  {
    "Lugares":"VILLA CAROLA - META"
  },
  {
    "Lugares":"VILLA DE LEYVA - BOYACA"
  },
  {
    "Lugares":"VILLA DEL ROSARIO - NORTE SANTANDER"
  },
  {
    "Lugares":"VILLA GARZON - PUTUMAYO"
  },
  {
    "Lugares":"VILLA GOMEZ - CUNDINAMARCA"
  },
  {
    "Lugares":"VILLA GORGONA - VALLE DEL CAUCA"
  },
  {
    "Lugares":"VILLA HERMOSA - TOLIMA"
  },
  {
    "Lugares":"VILLA MARIA - CALDAS"
  },
  {
    "Lugares":"VILLA MORENO - NARIÑO"
  },
  {
    "Lugares":"VILLA NUEVA - GUAJIRA"
  },
  {
    "Lugares":"VILLA VIEJA - HUILA"
  },
  {
    "Lugares":"VILLANUEVA - CASANARE"
  },
  {
    "Lugares":"VILLANUEVA - BOLIVAR"
  },
  {
    "Lugares":"VILLANUEVA - SANTANDER"
  },
  {
    "Lugares":"VILLAPINZON - CUNDINAMARCA"
  },
  {
    "Lugares":"VILLARRICA - CAUCA"
  },
  {
    "Lugares":"VILLARRICA - TOLIMA"
  },
  {
    "Lugares":"VILLAVICENCIO - META"
  },
  {
    "Lugares":"VILLETA - CUNDINAMARCA"
  },
  {
    "Lugares":"VIOTA - CUNDINAMARCA"
  },
  {
    "Lugares":"VIRACACHA - BOYACA"
  },
  {
    "Lugares":"VISTA HERMOSA - META"
  },
  {
    "Lugares":"VITERBO - CALDAS"
  },
  {
    "Lugares":"YACOPI - CUNDINAMARCA"
  },
  {
    "Lugares":"YACUANQUER - NARIÑO"
  },
  {
    "Lugares":"YAGUARA - HUILA"
  },
  {
    "Lugares":"YALI - ANTIOQUIA"
  },
  {
    "Lugares":"YARIMA - SANTANDER"
  },
  {
    "Lugares":"YARUMAL - ANTIOQUIA"
  },
  {
    "Lugares":"YATI - BOLIVAR"
  },
  {
    "Lugares":"YOLOMBO - ANTIOQUIA"
  },
  {
    "Lugares":"YONDO - ANTIOQUIA"
  },
  {
    "Lugares":"YOPAL - CASANARE"
  },
  {
    "Lugares":"YOPALOSA - CASANARE"
  },
  {
    "Lugares":"YOTOCO - VALLE DEL CAUCA"
  },
  {
    "Lugares":"YUMBO - VALLE DEL CAUCA"
  },
  {
    "Lugares":"YUTO - CHOCO"
  },
  {
    "Lugares":"ZAMBRANO - BOLIVAR"
  },
  {
    "Lugares":"ZAPATOCA - SANTANDER"
  },
  {
    "Lugares":"ZARAGOZA - VALLE DEL CAUCA"
  },
  {
    "Lugares":"ZARAGOZA - ANTIOQUIA"
  },
  {
    "Lugares":"ZARZAL - VALLE DEL CAUCA"
  },
  {
    "Lugares":"ZETAQUIRA - BOYACA"
  },
  {
    "Lugares":"ZIPACON - CUNDINAMARCA"
  },
  {
    "Lugares":"ZIPAQUIRA - CUNDINAMARCA"
  },
  {
    "Lugares":"LA GRAN VIA - MAGDALENA"
  },
  {
    "Lugares":"SAN JOAQUIN - CUNDINAMARCA"
  },
  {
    "Lugares":"PRADILLA - CUNDINAMARCA"
  },
  {
    "Lugares":"LA VICTORIA - VALLE DEL CAUCA"
  },
  {
    "Lugares":"SANTANDERSITO - CUNDINAMARCA"
  },
  {
    "Lugares":"SAN ANTONIO - TOLIMA"
  },
  {
    "Lugares":"SAN REIMUNDO - CUNDINAMARCA"
  },
  {
    "Lugares":"LA AGADITA - CUNDINAMARCA"
  },
  {
    "Lugares":"BARRANCA DE UPIA - META"
  },
  {
    "Lugares":"SAN LUIS DE GACENO - BOYACA"
  },
  {
    "Lugares":"HATOCOROZAL - CASANARE"
  },
  {
    "Lugares":"EL RETORNO - GUAVIARE"
  },
  {
    "Lugares":"CARANAL - ARAUCA"
  },
  {
    "Lugares":"PUEBLO NUEVO - CORDOBA"
  },
  {
    "Lugares":"BANADIA - ARAUCA"
  },
  {
    "Lugares":"PANAMA - ARAUCA"
  },
  {
    "Lugares":"CARMEN DE VIVORAL - ANTIOQUIA"
  },
  {
    "Lugares":"CHINVITA - BOYACA"
  },
  {
    "Lugares":"ASERNA NUEVO - VALLE DEL CAUCA"
  },
  {
    "Lugares":"EL DOS - CHOCO"
  },
  {
    "Lugares":"PLAYA DE ORO - CHOCO"
  },
  {
    "Lugares":"AGUA LINDA - NORTE SANTANDER"
  },
  {
    "Lugares":"AGUACLARA - VALLE DEL CAUCA"
  },
  {
    "Lugares":"ALBANIA - SANTANDER"
  },
  {
    "Lugares":"ALTO CORINTO - CALDAS"
  },
  {
    "Lugares":"ALTO JORDAN - SANTANDER"
  },
  {
    "Lugares":"ALTO POMPEYA - META"
  },
  {
    "Lugares":"ALTO TABLAZO - CALDAS"
  },
  {
    "Lugares":"ANSERMANUEVO - VALLE DEL CAUCA"
  },
  {
    "Lugares":"ARROYOHONDO - VALLE DEL CAUCA"
  },
  {
    "Lugares":"ATUNCELA - VALLE DEL CAUCA"
  },
  {
    "Lugares":"BAJO CORINTO - CALDAS"
  },
  {
    "Lugares":"BAJO JORDAN - SANTANDER"
  },
  {
    "Lugares":"BELLA VISTA - NARIÑO"
  },
  {
    "Lugares":"BELLAVISTA - NARIÑO"
  },
  {
    "Lugares":"BENDICIONES - VALLE DEL CAUCA"
  },
  {
    "Lugares":"BERLIN - CALDAS"
  },
  {
    "Lugares":"BOMBONA - NARIÑO"
  },
  {
    "Lugares":"BONAFONT - CALDAS"
  },
  {
    "Lugares":"BUENOS AIRES - HUILA"
  },
  {
    "Lugares":"BUENOS AIRES - PUTUMAYO"
  },
  {
    "Lugares":"CABO DE LA VELA - GUAJIRA"
  },
  {
    "Lugares":"CABUYALES - NARIÑO"
  },
  {
    "Lugares":"CABUYARO - META"
  },
  {
    "Lugares":"CALAMAR - GUAVIARE"
  },
  {
    "Lugares":"CALIFORNIA - SANTANDER"
  },
  {
    "Lugares":"CAMBAO - CUNDINAMARCA"
  },
  {
    "Lugares":"CAMPO DOS - NORTE SANTANDER"
  },
  {
    "Lugares":"CAMPOALEGRE - VALLE DEL CAUCA"
  },
  {
    "Lugares":"CANALETE URBANO - CORDOBA"
  },
  {
    "Lugares":"CANDELILLAS - NARIÑO"
  },
  {
    "Lugares":"CARACOLI - CESAR"
  },
  {
    "Lugares":"CAROLINA - ANTIOQUIA"
  },
  {
    "Lugares":"CARRAIPIA - GUAJIRA"
  },
  {
    "Lugares":"CARTAGENA - NARIÑO"
  },
  {
    "Lugares":"CASABE - ANTIOQUIA"
  },
  {
    "Lugares":"CHARTA - SANTANDER"
  },
  {
    "Lugares":"CHILES - NARIÑO"
  },
  {
    "Lugares":"CHIVOLO - MAGDALENA"
  },
  {
    "Lugares":"CHONTADURO - VALLE DEL CAUCA"
  },
  {
    "Lugares":"CICUCO - BOLIVAR"
  },
  {
    "Lugares":"CONCEPCION - META"
  },
  {
    "Lugares":"CONVENIO - TOLIMA"
  },
  {
    "Lugares":"CORDOBA - VALLE DEL CAUCA"
  },
  {
    "Lugares":"CORNEJO - NORTE SANTANDER"
  },
  {
    "Lugares":"CORONADO - VALLE DEL CAUCA"
  },
  {
    "Lugares":"COSCUEZ - BOYACA"
  },
  {
    "Lugares":"CRUZ DEL VIZO - BOLIVAR"
  },
  {
    "Lugares":"CUASPUD NUCLEO - NARIÑO"
  },
  {
    "Lugares":"DINAMARCA - META"
  },
  {
    "Lugares":"EL ARENAL - VALLE DEL CAUCA"
  },
  {
    "Lugares":"EL ARENILLO - CALDAS"
  },
  {
    "Lugares":"EL CALVARIO - META"
  },
  {
    "Lugares":"EL CARMEN DE CHUCURI - SANTANDER"
  },
  {
    "Lugares":"EL DIAMANTE - NORTE SANTANDER"
  },
  {
    "Lugares":"EL DIVISO - NARIÑO"
  },
  {
    "Lugares":"EL EJIDO - NARIÑO"
  },
  {
    "Lugares":"EL EMPATE - NARIÑO"
  },
  {
    "Lugares":"EL HORMIGUERO - VALLE DEL CAUCA"
  },
  {
    "Lugares":"EL INGENIO - NARIÑO"
  },
  {
    "Lugares":"EL INGENIO - VALLE DEL CAUCA"
  },
  {
    "Lugares":"EL JARDIN - ANTIOQUIA"
  },
  {
    "Lugares":"EL LIMON - TOLIMA"
  },
  {
    "Lugares":"EL NUEVO DIAMANTE - NORTE DE SANTANDE"
  },
  {
    "Lugares":"EL PALMAR - VALLE DEL CAUCA"
  },
  {
    "Lugares":"EL PEDREGAL - VALLE DEL CAUCA"
  },
  {
    "Lugares":"EL PEPINO - PUTUMAYO"
  },
  {
    "Lugares":"EL PORVENIR - VALLE DEL CAUCA"
  },
  {
    "Lugares":"EL RETORNO - GUAVIARE"
  },
  {
    "Lugares":"EL SALADO - VALLE DEL CAUCA"
  },
  {
    "Lugares":"EL SILENCIO - VALLE DEL CAUCA"
  },
  {
    "Lugares":"EL TIPLE - VALLE DEL CAUCA"
  },
  {
    "Lugares":"EL TRAPICHE - NORTE SANTANDER"
  },
  {
    "Lugares":"EL VINCULO - VALLE DEL CAUCA"
  },
  {
    "Lugares":"ELIAS - HUILA"
  },
  {
    "Lugares":"FELIDIA - VALLE DEL CAUCA"
  },
  {
    "Lugares":"GAITANIA - TOLIMA"
  },
  {
    "Lugares":"GOLONDRINAS - VALLE DEL CAUCA"
  },
  {
    "Lugares":"GRANADA - MAGDALENA"
  },
  {
    "Lugares":"GUABAS - VALLE DEL CAUCA"
  },
  {
    "Lugares":"GUABITAS - VALLE DEL CAUCA"
  },
  {
    "Lugares":"GUADALAJARA DE BUGA - VALLE DEL CAUCA"
  },
  {
    "Lugares":"GUADUERO - CUNDINAMARCA"
  },
  {
    "Lugares":"GUANE - SANTANDER"
  },
  {
    "Lugares":"GUAPI - CAUCA"
  },
  {
    "Lugares":"GUARUMO - ANTIOQUIA"
  },
  {
    "Lugares":"GUAYABAL - VALLE DEL CAUCA"
  },
  {
    "Lugares":"GÜICAN DE LA SIERRA - BOYACA"
  },
  {
    "Lugares":"HACARI - NORTE SANTANDER"
  },
  {
    "Lugares":"HATONUEVO - GUAJIRA"
  },
  {
    "Lugares":"HOLGUIN - VALLE DEL CAUCA"
  },
  {
    "Lugares":"ISAZA - CALDAS"
  },
  {
    "Lugares":"JERUSALEN - CUNDINAMARCA"
  },
  {
    "Lugares":"JOSE MARIA HERNANDEZ - NARIÑO"
  },
  {
    "Lugares":"LA ALBANIA - VALLE DEL CAUCA"
  },
  {
    "Lugares":"LA ALEJANDRA - NORTE SANTANDER"
  },
  {
    "Lugares":"LA APARTADA Y LA FRONTERA - CORDOBA"
  },
  {
    "Lugares":"LA CALDERA - NARIÑO"
  },
  {
    "Lugares":"LA CUCHILLA DEL SALADO - CALDAS"
  },
  {
    "Lugares":"LA DELFINA - VALLE DEL CAUCA"
  },
  {
    "Lugares":"LA FLORESTA - NORTE SANTANDER"
  },
  {
    "Lugares":"LA FLORESTA - VALLE DEL CAUCA"
  },
  {
    "Lugares":"LA GABARRA - NORTE SANTANDER"
  },
  {
    "Lugares":"LA GARITA - NORTE SANTANDER"
  },
  {
    "Lugares":"LA LEONERA - VALLE DEL CAUCA"
  },
  {
    "Lugares":"LA MARIA - VALLE DEL CAUCA"
  },
  {
    "Lugares":"LA MARINA - VALLE DEL CAUCA"
  },
  {
    "Lugares":"LA MATA - CESAR"
  },
  {
    "Lugares":"LA NUEVA DONJUANA - NORTE DE SANTANDER"
  },
  {
    "Lugares":"LA PLANADA - NARIÑO"
  },
  {
    "Lugares":"LA PLATA - NARIÑO"
  },
  {
    "Lugares":"LA REGINA - VALLE DEL CAUCA"
  },
  {
    "Lugares":"LA TUPIA - VALLE DEL CAUCA"
  },
  {
    "Lugares":"LA UNION PENEYA - CAQUETA"
  },
  {
    "Lugares":"LA VEGA - CAUCA"
  },
  {
    "Lugares":"LA YE - SAN MIGUEL - NORTE SANTANDER"
  },
  {
    "Lugares":"LAS CRUCES - NARIÑO"
  },
  {
    "Lugares":"LIMONCITOS - CUNDINAMARCA"
  },
  {
    "Lugares":"LLANOS DE CUIVA - ANTIOQUIA"
  },
  {
    "Lugares":"LOMA DE ARENA - BOLIVAR"
  },
  {
    "Lugares":"LOMITAS - VALLE DEL CAUCA"
  },
  {
    "Lugares":"LOS ARRAYANES - NARIÑO"
  },
  {
    "Lugares":"LOS VADOS - NORTE SANTANDER"
  },
  {
    "Lugares":"MAGUI - PAYAN"
  },
  {
    "Lugares":"MAPIRIPAN - META"
  },
  {
    "Lugares":"MARIANGOLA - CESAR"
  },
  {
    "Lugares":"MATANZA - SANTANDER"
  },
  {
    "Lugares":"MAYA - CUNDINAMARCA"
  },
  {
    "Lugares":"MEDIACANOA - VALLE DEL CAUCA"
  },
  {
    "Lugares":"MILAN - CAQUETA"
  },
  {
    "Lugares":"MIRAFLORES - GUAVIARE"
  },
  {
    "Lugares":"MIRAVALLE DAPA - VALLE DEL CAUCA"
  },
  {
    "Lugares":"MONTAÑITAS - VALLE DEL CAUCA"
  },
  {
    "Lugares":"MONTEBONITO - CALDAS"
  },
  {
    "Lugares":"MONTECRISTO - BOLIVAR"
  },
  {
    "Lugares":"NARIÑO - VALLE DEL CAUCA"
  },
  {
    "Lugares":"NECHI - ANTIOQUIA"
  },
  {
    "Lugares":"ONZAGA - SANTANDER"
  },
  {
    "Lugares":"ORIPAYA - NORTE SANTANDER"
  },
  {
    "Lugares":"PALERMO - BOYACA"
  },
  {
    "Lugares":"PANTANO DE VARGAS - BOYACA"
  },
  {
    "Lugares":"PARAGUACHON - GUAJIRA"
  },
  {
    "Lugares":"PASO DE LA BOLSA - VALLE DEL CAUCA"
  },
  {
    "Lugares":"PATILLALES - NORTE SANTANDER"
  },
  {
    "Lugares":"PETROLEA - NORTE SANTANDER"
  },
  {
    "Lugares":"PIEDECUESTA - SANTANDER"
  },
  {
    "Lugares":"PIEDRANCHA - NARIÑO"
  },
  {
    "Lugares":"PILCUAN VIEJO - 2"
  },
  {
    "Lugares":"PINILLOS - BOLIVAR"
  },
  {
    "Lugares":"PINZON - NARIÑO"
  },
  {
    "Lugares":"PLAYA MENDOZA - ATLANTICO"
  },
  {
    "Lugares":"PLAYARRICA - TOLIMA"
  },
  {
    "Lugares":"PORTUGAL DE PIEDRAS - VALLE DEL CAUCA"
  },
  {
    "Lugares":"PUEBLO NUEVO - CAUCA"
  },
  {
    "Lugares":"PUENTE QUETAME - CUNDINAMARCA"
  },
  {
    "Lugares":"PUERTO COLON - PUTUMAYO"
  },
  {
    "Lugares":"PUERTO LLERAS - NORTE SANTANDER"
  },
  {
    "Lugares":"PUERTO RICO - ANTIOQUIA"
  },
  {
    "Lugares":"PUERTO UMBRIA - PUTUMAYO"
  },
  {
    "Lugares":"PURISIMA DE LA CONCEPCION - CORDOBA"
  },
  {
    "Lugares":"RECTA LOS ALAMOS - NORTE SANTANDER"
  },
  {
    "Lugares":"REMOLINO - MAGDALENA"
  },
  {
    "Lugares":"RICAURTE - COLOSO"
  },
  {
    "Lugares":"RIONEGRO - CAQUETA"
  },
  {
    "Lugares":"RIOSUCIO - CHOCO"
  },
  {
    "Lugares":"RONCESVALLES - TOLIMA"
  },
  {
    "Lugares":"SALONICA - VALLE DEL CAUCA"
  },
  {
    "Lugares":"SAN ANTONIO - VALLE DEL CAUCA"
  },
  {
    "Lugares":"SAN ANTONIO DE ANAPOIMA - CUNDINAMARCA"
  },
  {
    "Lugares":"SAN ANTONIO DE GETUCHA - CAQUETA"
  },
  {
    "Lugares":"SAN ANTONIO DE LOS CABALLEROS - VALLE DEL CAUCA"
  },
  {
    "Lugares":"SAN BENITO ABAD - SUCRE"
  },
  {
    "Lugares":"SAN CARLOS - CORDOBA"
  },
  {
    "Lugares":"SAN CARLOS DE GUAROA - META"
  },
  {
    "Lugares":"SAN CIPRIANO - VALLE DEL CAUCA"
  },
  {
    "Lugares":"SAN DANIEL - CALDAS"
  },
  {
    "Lugares":"SAN DIEGO - CALDAS"
  },
  {
    "Lugares":"SAN FRANCISCO - HUILA"
  },
  {
    "Lugares":"SAN FRANCISCO - VALLE DEL CAUCA"
  },
  {
    "Lugares":"SAN FRANCISCO DE LA SIERRA - TOLIMA"
  },
  {
    "Lugares":"SAN FRANCISCO DE QUIBDO - CHOCO"
  },
  {
    "Lugares":"SAN JACINTO - BOLIVAR"
  },
  {
    "Lugares":"SAN JOAQUIN - CUNDINAMARCA"
  },
  {
    "Lugares":"SAN JOSE - RISARALDA"
  },
  {
    "Lugares":"SAN JOSE DE ISNOS - HUILA"
  },
  {
    "Lugares":"SAN JUAN DE RIOSECO - CUNDINAMARCA"
  },
  {
    "Lugares":"SAN JUANITO - META"
  },
  {
    "Lugares":"SAN LORENZO - CALDAS"
  },
  {
    "Lugares":"SAN LORENZO - META"
  },
  {
    "Lugares":"SAN LUIS - CUNDINAMARCA"
  },
  {
    "Lugares":"SAN LUIS - NARIÑO"
  },
  {
    "Lugares":"SAN MIGUEL - NARIÑO"
  },
  {
    "Lugares":"SAN ROQUE - SUCRE"
  },
  {
    "Lugares":"SAN SEBASTIAN DE BUENAVISTA - MAGDALENA"
  },
  {
    "Lugares":"SAN SEBASTIAN DE MARIQUITA - TOLIMA"
  },
  {
    "Lugares":"SAN ZENON - MAGDALENA"
  },
  {
    "Lugares":"SANTA ANA - RISARALDA"
  },
  {
    "Lugares":"SANTA CRUZ DE LORICA - CORDOBA"
  },
  {
    "Lugares":"SANTA CRUZ DE MOMPOX - BOLIVAR"
  },
  {
    "Lugares":"SANTA HELENA DEL OPON - SANTANDER"
  },
  {
    "Lugares":"SANTA ROSA - NARIÑO"
  },
  {
    "Lugares":"SANTA ROSALIA - MAGDALENA"
  },
  {
    "Lugares":"SANTANA - PUTUMAYO"
  },
  {
    "Lugares":"SANTIAGO - ANTIOQUIA"
  },
  {
    "Lugares":"SANTIAGO PEREZ - TOLIMA"
  },
  {
    "Lugares":"SEVILLA ZONA BANANERA - MAGDALENA"
  },
  {
    "Lugares":"SIBERIA - CAUCA"
  },
  {
    "Lugares":"SOLANO - CAQUETA"
  },
  {
    "Lugares":"SOLITA - CAQUETA"
  },
  {
    "Lugares":"SUCRE - SUCRE"
  },
  {
    "Lugares":"SUEVA - CUNDINAMARCA"
  },
  {
    "Lugares":"SURATA - SANTANDER"
  },
  {
    "Lugares":"TAJUMBINA - NARIÑO"
  },
  {
    "Lugares":"TASNAQUE - NARIÑO"
  },
  {
    "Lugares":"TIERRA BAJA - BOLIVAR"
  },
  {
    "Lugares":"TIMBA - VALLE DEL CAUCA"
  },
  {
    "Lugares":"TOBIA - LA MILAGROSA - CUNDINAMARCA"
  },
  {
    "Lugares":"TODOS LOS SANTOS - VALLE DEL CAUCA"
  },
  {
    "Lugares":"TONA - SANTANDER"
  },
  {
    "Lugares":"TRES ESQUINAS - VALLE DEL CAUCA"
  },
  {
    "Lugares":"TUNJA GRANDE - NARIÑO"
  },
  {
    "Lugares":"UNGUIA - CHOCO"
  },
  {
    "Lugares":"URAMITA - ANTIOQUIA"
  },
  {
    "Lugares":"URIBE - META"
  },
  {
    "Lugares":"URIMACO - NORTE SANTANDER"
  },
  {
    "Lugares":"VALLE DE GAIRA - MAGDALENA"
  },
  {
    "Lugares":"VALPARAISO - CAQUETA"
  },
  {
    "Lugares":"VETAS - SANTANDER"
  },
  {
    "Lugares":"VILLARICA - CAUCA"
  },
  {
    "Lugares":"VILLA VANEGAS - VALLE DEL CAUCA"
  },
  {
    "Lugares":"VILLACARMELO - VALLE DEL CAUCA"
  },
  {
    "Lugares":"VILLAHERMOSA - TOLIMA"
  },
  {
    "Lugares":"YARUMO - PUTUMAYO"
  },
  {
    "Lugares":"YASCUAL - NARIÑO"
  },
  {
    "Lugares":"YUMBILLO - VALLE DEL CAUCA"
  },
  {
    "Lugares":"ZANJON HONDO - VALLE DEL CAUCA"
  }
]